{"intersections": {"sin__x__sin": [{"Fecha": "21-04-2020", "Región": "La Araucanía", "Comuna": "LUMACO", "Urbano/Rural": "RURAL", "Calleuno": "Sin especificar", "Calledos": "Sin especificar", "Ubicación/km": "5", "Siniestros": "Colisión", "Causas": "Conducción no atento condiciones transito momento", "Fallecidos": "0", "Graves": "0", "M/Grave": "0", "Leves": "0", "Ilesos": "2"}, {"Fecha": "27-04-2020", "Región": "La Araucanía", "Comuna": "LUMACO", "Urbano/Rural": "RURAL", "Calleuno": "Sin especificar", "Calledos": "Sin especificar", "Ubicación/km": "4", "Siniestros": "Volcadura", "Causas": "Conducción en estado de ebriedad", "Fallecidos": "0", "Graves": "0", "M/Grave": "1", "Leves": "0", "Ilesos": "0"}, {"Fecha": "04-05-2020", "Región": "La Araucanía", "Comuna": "LUMACO", "Urbano/Rural": "RURAL", "Calleuno": "Sin especificar", "Calledos": "Sin especificar", "Ubicación/km": "2", "Siniestros": "Volcadura", "Causas": "Conducción no atento condiciones transito momento", "Fallecidos": "0", "Graves": "0", "M/Grave": "0", "Leves": "0", "Ilesos": "2"}, {"Fecha": "06-05-2020", "Región": "La Araucanía", "Comuna": "LUMACO", "Urbano/Rural": "RURAL", "Calleuno": "Sin especificar", "Calledos": "Sin especificar", "Ubicación/km": "4", "Siniestros": "Colisión", "Causas": "Conducción no atento condiciones transito momento", "Fallecidos": "0", "Graves": "0", "M/Grave": "0", "Leves": "0", "Ilesos": "2"}, {"Fecha": "21-05-2020", "Región": "La Araucanía", "Comuna": "LUMACO", "Urbano/Rural": "RURAL", "Calleuno": "Sin especificar", "Calledos": "Sin especificar", "Ubicación/km": "4", "Siniestros": "Choque", "Causas": "Fallas mecánicas, frenos", "Fallecidos": "0", "Graves": "0", "M/Grave": "1", "Leves": "0", "Ilesos": "1"}, {"Fecha": "01-06-2020", "Región": "La Araucanía", "Comuna": "LUMACO", "Urbano/Rural": "RURAL", "Calleuno": "Sin especificar", "Calledos": "Sin especificar", "Ubicación/km": "3", "Siniestros": "Colisión", "Causas": "Conducción en estado de ebriedad", "Fallecidos": "0", "Graves": "1", "M/Grave": "0", "Leves": "1", "Ilesos": "1"}, {"Fecha": "05-06-2020", "Región": "La Araucanía", "Comuna": "LUMACO", "Urbano/Rural": "RURAL", "Calleuno": "Sin especificar", "Calledos": "Sin especificar", "Ubicación/km": "1", "Siniestros": "Choque", "Causas": "Animales sueltos via publica", "Fallecidos": "0", "Graves": "0", "M/Grave": "0", "Leves": "0", "Ilesos": "1"}, {"Fecha": "08-06-2020", "Región": "La Araucanía", "Comuna": "LUMACO", "Urbano/Rural": "RURAL", "Calleuno": "Sin especificar", "Calledos": "Sin especificar", "Ubicación/km": "5", "Siniestros": "Choque", "Causas": "Perdida control vehículo", "Fallecidos": "0", "Graves": "0", "M/Grave": "0", "Leves": "0", "Ilesos": "1"}, {"Fecha": "21-08-2020", "Región": "La Araucanía", "Comuna": "LUMACO", "Urbano/Rural": "RURAL", "Calleuno": "Sin especificar", "Calledos": "Sin especificar", "Ubicación/km": "8", "Siniestros": "Colisión", "Causas": "Otras causas", "Fallecidos": "0", "Graves": "0", "M/Grave": "0", "Leves": "0", "Ilesos": "3"}, {"Fecha": "29-08-2020", "Región": "La Araucanía", "Comuna": "LUMACO", "Urbano/Rural": "RURAL", "Calleuno": "Sin especificar", "Calledos": "Sin especificar", "Ubicación/km": "None", "Siniestros": "Choque", "Causas": "Causas no determinadas", "Fallecidos": "0", "Graves": "0", "M/Grave": "0", "Leves": "1", "Ilesos": "1"}, {"Fecha": "27-10-2020", "Región": "La Araucanía", "Comuna": "LUMACO", "Urbano/Rural": "RURAL", "Calleuno": "Sin especificar", "Calledos": "Sin especificar", "Ubicación/km": "1", "Siniestros": "Colisión", "Causas": "Conducción bajo la influencia del alcohol", "Fallecidos": "0", "Graves": "0", "M/Grave": "0", "Leves": "0", "Ilesos": "2"}, {"Fecha": "09-12-2020", "Región": "La Araucanía", "Comuna": "LUMACO", "Urbano/Rural": "RURAL", "Calleuno": "Sin especificar", "Calledos": "Sin especificar", "Ubicación/km": "2", "Siniestros": "Colisión", "Causas": "Otras causas", "Fallecidos": "0", "Graves": "0", "M/Grave": "0", "Leves": "0", "Ilesos": "2"}, {"Fecha": "28-12-2020", "Región": "La Araucanía", "Comuna": "LUMACO", "Urbano/Rural": "RURAL", "Calleuno": "Sin especificar", "Calledos": "Sin especificar", "Ubicación/km": "5", "Siniestros": "Choque", "Causas": "Conducción en estado de ebriedad", "Fallecidos": "0", "Graves": "0", "M/Grave": "1", "Leves": "1", "Ilesos": "0"}, {"Fecha": "29-12-2020", "Región": "La Araucanía", "Comuna": "LUMACO", "Urbano/Rural": "RURAL", "Calleuno": "Sin especificar", "Calledos": "Sin especificar", "Ubicación/km": "None", "Siniestros": "Colisión", "Causas": "Conducción no atento condiciones transito momento", "Fallecidos": "0", "Graves": "0", "M/Grave": "0", "Leves": "3", "Ilesos": "2"}, {"Fecha": "28-01-2021", "Región": "La Araucanía", "Comuna": "LUMACO", "Urbano/Rural": "RURAL", "Calleuno": "Sin especificar", "Calledos": "Sin especificar", "Ubicación/km": "5", "Siniestros": "Colisión", "Causas": "Perdida control vehículo", "Fallecidos": "0", "Graves": "0", "M/Grave": "0", "Leves": "0", "Ilesos": "2"}, {"Fecha": "20-02-2021", "Región": "La Araucanía", "Comuna": "LUMACO", "Urbano/Rural": "RURAL", "Calleuno": "Sin especificar", "Calledos": "Sin especificar", "Ubicación/km": "3", "Siniestros": "Volcadura", "Causas": "Fallas mecánicas, frenos", "Fallecidos": "0", "Graves": "0", "M/Grave": "0", "Leves": "0", "Ilesos": "1"}, {"Fecha": "23-02-2021", "Región": "La Araucanía", "Comuna": "LUMACO", "Urbano/Rural": "RURAL", "Calleuno": "Sin especificar", "Calledos": "Sin especificar", "Ubicación/km": "6", "Siniestros": "Choque", "Causas": "Animales sueltos via publica", "Fallecidos": "0", "Graves": "0", "M/Grave": "0", "Leves": "0", "Ilesos": "1"}, {"Fecha": "03-05-2021", "Región": "La Araucanía", "Comuna": "LUMACO", "Urbano/Rural": "RURAL", "Calleuno": "Sin especificar", "Calledos": "Sin especificar", "Ubicación/km": "26", "Siniestros": "Volcadura", "Causas": "Velocidad, no reducir cruce de calles, cumbre, curva,etc.", "Fallecidos": "1", "Graves": "0", "M/Grave": "0", "Leves": "0", "Ilesos": "0"}, {"Fecha": "04-05-2021", "Región": "La Araucanía", "Comuna": "LUMACO", "Urbano/Rural": "RURAL", "Calleuno": "Sin especificar", "Calledos": "Sin especificar", "Ubicación/km": "4", "Siniestros": "Colisión", "Causas": "Conducción, cambiar sorpresivamente pista circulación", "Fallecidos": "1", "Graves": "0", "M/Grave": "0", "Leves": "1", "Ilesos": "0"}, {"Fecha": "28-05-2021", "Región": "La Araucanía", "Comuna": "LUMACO", "Urbano/Rural": "RURAL", "Calleuno": "Sin especificar", "Calledos": "Sin especificar", "Ubicación/km": "2", "Siniestros": "Otros", "Causas": "Otras causas", "Fallecidos": "0", "Graves": "0", "M/Grave": "0", "Leves": "0", "Ilesos": "1"}, {"Fecha": "17-06-2021", "Región": "La Araucanía", "Comuna": "LUMACO", "Urbano/Rural": "RURAL", "Calleuno": "Sin especificar", "Calledos": "Sin especificar", "Ubicación/km": "19.05", "Siniestros": "Volcadura", "Causas": "Causas no determinadas", "Fallecidos": "0", "Graves": "1", "M/Grave": "0", "Leves": "0", "Ilesos": "0"}, {"Fecha": "20-06-2021", "Región": "La Araucanía", "Comuna": "LUMACO", "Urbano/Rural": "RURAL", "Calleuno": "Sin especificar", "Calledos": "Sin especificar", "Ubicación/km": "10", "Siniestros": "Colisión", "Causas": "Conducción no atento condiciones transito momento", "Fallecidos": "0", "Graves": "0", "M/Grave": "0", "Leves": "3", "Ilesos": "0"}, {"Fecha": "03-09-2021", "Región": "La Araucanía", "Comuna": "LUMACO", "Urbano/Rural": "RURAL", "Calleuno": "Sin especificar", "Calledos": "Sin especificar", "Ubicación/km": "3", "Siniestros": "Colisión", "Causas": "Conducción no atento condiciones transito momento", "Fallecidos": "0", "Graves": "0", "M/Grave": "0", "Leves": "0", "Ilesos": "2"}, {"Fecha": "04-09-2021", "Región": "La Araucanía", "Comuna": "LUMACO", "Urbano/Rural": "RURAL", "Calleuno": "Sin especificar", "Calledos": "Sin especificar", "Ubicación/km": "9", "Siniestros": "Volcadura", "Causas": "Otras causas", "Fallecidos": "0", "Graves": "0", "M/Grave": "0", "Leves": "1", "Ilesos": "0"}, {"Fecha": "11-09-2021", "Región": "La Araucanía", "Comuna": "LUMACO", "Urbano/Rural": "RURAL", "Calleuno": "Sin especificar", "Calledos": "Sin especificar", "Ubicación/km": "15", "Siniestros": "Colisión", "Causas": "Conducción no atento condiciones transito momento", "Fallecidos": "1", "Graves": "0", "M/Grave": "1", "Leves": "1", "Ilesos": "0"}, {"Fecha": "18-10-2021", "Región": "La Araucanía", "Comuna": "LUMACO", "Urbano/Rural": "RURAL", "Calleuno": "Sin especificar", "Calledos": "Sin especificar", "Ubicación/km": "9", "Siniestros": "Choque", "Causas": "Animales sueltos via publica", "Fallecidos": "0", "Graves": "0", "M/Grave": "0", "Leves": "0", "Ilesos": "1"}, {"Fecha": "27-10-2021", "Región": "La Araucanía", "Comuna": "LUMACO", "Urbano/Rural": "RURAL", "Calleuno": "Sin especificar", "Calledos": "Sin especificar", "Ubicación/km": "2", "Siniestros": "Volcadura", "Causas": "Causas no determinadas", "Fallecidos": "0", "Graves": "0", "M/Grave": "0", "Leves": "5", "Ilesos": "0"}, {"Fecha": "19-11-2021", "Región": "La Araucanía", "Comuna": "LUMACO", "Urbano/Rural": "RURAL", "Calleuno": "Sin especificar", "Calledos": "Sin especificar", "Ubicación/km": "4", "Siniestros": "Volcadura", "Causas": "Perdida control vehículo", "Fallecidos": "0", "Graves": "0", "M/Grave": "0", "Leves": "1", "Ilesos": "0"}, {"Fecha": "26-12-2021", "Región": "La Araucanía", "Comuna": "LUMACO", "Urbano/Rural": "RURAL", "Calleuno": "Sin especificar", "Calledos": "Sin especificar", "Ubicación/km": "12", "Siniestros": "Atropello", "Causas": "Causas no determinadas", "Fallecidos": "0", "Graves": "0", "M/Grave": "1", "Leves": "0", "Ilesos": "1"}, {"Fecha": "03-02-2022", "Región": "La Araucanía", "Comuna": "LUMACO", "Urbano/Rural": "RURAL", "Calleuno": "Sin especificar", "Calledos": "Sin especificar", "Ubicación/km": "4", "Siniestros": "Choque", "Causas": "Conducción en estado de ebriedad", "Fallecidos": "0", "Graves": "0", "M/Grave": "0", "Leves": "1", "Ilesos": "0"}, {"Fecha": "11-02-2022", "Región": "La Araucanía", "Comuna": "LUMACO", "Urbano/Rural": "RURAL", "Calleuno": "Sin especificar", "Calledos": "Sin especificar", "Ubicación/km": "3", "Siniestros": "Volcadura", "Causas": "Perdida control vehículo", "Fallecidos": "0", "Graves": "0", "M/Grave": "0", "Leves": "1", "Ilesos": "0"}, {"Fecha": "13-02-2022", "Región": "La Araucanía", "Comuna": "LUMACO", "Urbano/Rural": "RURAL", "Calleuno": "Sin especificar", "Calledos": "Sin especificar", "Ubicación/km": "1", "Siniestros": "Choque", "Causas": "Conducción en estado de ebriedad", "Fallecidos": "0", "Graves": "0", "M/Grave": "0", "Leves": "1", "Ilesos": "0"}, {"Fecha": "15-02-2022", "Región": "La Araucanía", "Comuna": "LUMACO", "Urbano/Rural": "RURAL", "Calleuno": "Sin especificar", "Calledos": "Sin especificar", "Ubicación/km": "5", "Siniestros": "Volcadura", "Causas": "Condiciones físicas deficientes (cansancio, sueño)", "Fallecidos": "0", "Graves": "0", "M/Grave": "0", "Leves": "1", "Ilesos": "0"}, {"Fecha": "23-02-2022", "Región": "La Araucanía", "Comuna": "LUMACO", "Urbano/Rural": "RURAL", "Calleuno": "Sin especificar", "Calledos": "Sin especificar", "Ubicación/km": "10", "Siniestros": "Colisión", "Causas": "Velocidad no razonable ni prudente", "Fallecidos": "0", "Graves": "0", "M/Grave": "0", "Leves": "0", "Ilesos": "2"}, {"Fecha": "04-03-2022", "Región": "La Araucanía", "Comuna": "LUMACO", "Urbano/Rural": "RURAL", "Calleuno": "Sin especificar", "Calledos": "Sin especificar", "Ubicación/km": "4", "Siniestros": "Colisión", "Causas": "Otras causas", "Fallecidos": "0", "Graves": "0", "M/Grave": "0", "Leves": "0", "Ilesos": "2"}, {"Fecha": "09-03-2022", "Región": "La Araucanía", "Comuna": "LUMACO", "Urbano/Rural": "RURAL", "Calleuno": "Sin especificar", "Calledos": "Sin especificar", "Ubicación/km": "11.8", "Siniestros": "Volcadura", "Causas": "Conducción en estado de ebriedad", "Fallecidos": "0", "Graves": "0", "M/Grave": "1", "Leves": "1", "Ilesos": "0"}, {"Fecha": "07-05-2022", "Región": "La Araucanía", "Comuna": "LUMACO", "Urbano/Rural": "RURAL", "Calleuno": "Sin especificar", "Calledos": "Sin especificar", "Ubicación/km": "3", "Siniestros": "Volcadura", "Causas": "Perdida control vehículo", "Fallecidos": "0", "Graves": "0", "M/Grave": "0", "Leves": "1", "Ilesos": "0"}, {"Fecha": "04-07-2022", "Región": "La Araucanía", "Comuna": "LUMACO", "Urbano/Rural": "RURAL", "Calleuno": "Sin especificar", "Calledos": "Sin especificar", "Ubicación/km": "9", "Siniestros": "Colisión", "Causas": "Conducción en estado de ebriedad", "Fallecidos": "0", "Graves": "0", "M/Grave": "0", "Leves": "1", "Ilesos": "1"}, {"Fecha": "08-09-2022", "Región": "La Araucanía", "Comuna": "LUMACO", "Urbano/Rural": "RURAL", "Calleuno": "Sin especificar", "Calledos": "Sin especificar", "Ubicación/km": "1", "Siniestros": "Choque", "Causas": "Animales sueltos vía publica", "Fallecidos": "0", "Graves": "0", "M/Grave": "0", "Leves": "1", "Ilesos": "0"}, {"Fecha": "16-09-2022", "Región": "La Araucanía", "Comuna": "LUMACO", "Urbano/Rural": "RURAL", "Calleuno": "Sin especificar", "Calledos": "Sin especificar", "Ubicación/km": "3", "Siniestros": "Volcadura", "Causas": "Perdida control vehículo", "Fallecidos": "0", "Graves": "0", "M/Grave": "0", "Leves": "2", "Ilesos": "0"}, {"Fecha": "06-10-2022", "Región": "La Araucanía", "Comuna": "LUMACO", "Urbano/Rural": "RURAL", "Calleuno": "Sin especificar", "Calledos": "Sin especificar", "Ubicación/km": "10", "Siniestros": "Volcadura", "Causas": "Otras causas", "Fallecidos": "0", "Graves": "0", "M/Grave": "0", "Leves": "0", "Ilesos": "1"}, {"Fecha": "16-10-2022", "Región": "La Araucanía", "Comuna": "LUMACO", "Urbano/Rural": "RURAL", "Calleuno": "Sin especificar", "Calledos": "Sin especificar", "Ubicación/km": "10", "Siniestros": "Choque", "Causas": "Perdida control vehículo", "Fallecidos": "0", "Graves": "0", "M/Grave": "1", "Leves": "0", "Ilesos": "0"}, {"Fecha": "29-12-2022", "Región": "La Araucanía", "Comuna": "LUMACO", "Urbano/Rural": "RURAL", "Calleuno": "Sin especificar", "Calledos": "Sin especificar", "Ubicación/km": "3", "Siniestros": "Volcadura", "Causas": "Fallas mecánicas, frenos", "Fallecidos": "0", "Graves": "1", "M/Grave": "0", "Leves": "2", "Ilesos": "1"}, {"Fecha": "21-01-2023", "Región": "La Araucanía", "Comuna": "LUMACO", "Urbano/Rural": "RURAL", "Calleuno": "Sin especificar", "Calledos": "Sin especificar", "Ubicación/km": "4", "Siniestros": "Colisión", "Causas": "Conducción sin mantener distancia razonable ni prudente", "Fallecidos": "1", "Graves": "1", "M/Grave": "0", "Leves": "1", "Ilesos": "0"}, {"Fecha": "02-02-2023", "Región": "La Araucanía", "Comuna": "LUMACO", "Urbano/Rural": "RURAL", "Calleuno": "Sin especificar", "Calledos": "Sin especificar", "Ubicación/km": "3", "Siniestros": "Volcadura", "Causas": "Velocidad, no reducir cruce de calles, cumbre, curva,etc.", "Fallecidos": "0", "Graves": "0", "M/Grave": "0", "Leves": "0", "Ilesos": "1"}, {"Fecha": "11-02-2023", "Región": "La Araucanía", "Comuna": "LUMACO", "Urbano/Rural": "RURAL", "Calleuno": "Sin especificar", "Calledos": "Sin especificar", "Ubicación/km": "3", "Siniestros": "Choque", "Causas": "Conducción no atento condiciones transito momento", "Fallecidos": "1", "Graves": "4", "M/Grave": "0", "Leves": "1", "Ilesos": "0"}, {"Fecha": "15-02-2023", "Región": "La Araucanía", "Comuna": "LUMACO", "Urbano/Rural": "RURAL", "Calleuno": "Sin especificar", "Calledos": "Sin especificar", "Ubicación/km": "5", "Siniestros": "Colisión", "Causas": "Conducción no atento condiciones transito momento", "Fallecidos": "0", "Graves": "0", "M/Grave": "0", "Leves": "0", "Ilesos": "2"}, {"Fecha": "13-03-2023", "Región": "La Araucanía", "Comuna": "LUMACO", "Urbano/Rural": "RURAL", "Calleuno": "Sin especificar", "Calledos": "Sin especificar", "Ubicación/km": "6", "Siniestros": "Colisión", "Causas": "Conducción no atento condiciones transito momento", "Fallecidos": "0", "Graves": "0", "M/Grave": "0", "Leves": "1", "Ilesos": "1"}, {"Fecha": "26-03-2023", "Región": "La Araucanía", "Comuna": "LUMACO", "Urbano/Rural": "RURAL", "Calleuno": "Sin especificar", "Calledos": "Sin especificar", "Ubicación/km": "11", "Siniestros": "Otros", "Causas": "Conducción bajo la influencia del alcohol", "Fallecidos": "0", "Graves": "0", "M/Grave": "0", "Leves": "1", "Ilesos": "1"}, {"Fecha": "03-04-2023", "Región": "La Araucanía", "Comuna": "LUMACO", "Urbano/Rural": "RURAL", "Calleuno": "Sin especificar", "Calledos": "Sin especificar", "Ubicación/km": "11", "Siniestros": "Colisión", "Causas": "Conducción no atento condiciones transito momento", "Fallecidos": "0", "Graves": "0", "M/Grave": "0", "Leves": "0", "Ilesos": "2"}, {"Fecha": "06-04-2023", "Región": "La Araucanía", "Comuna": "LUMACO", "Urbano/Rural": "RURAL", "Calleuno": "Sin especificar", "Calledos": "Sin especificar", "Ubicación/km": "4", "Siniestros": "Choque", "Causas": "Animales sueltos via publica", "Fallecidos": "0", "Graves": "0", "M/Grave": "1", "Leves": "0", "Ilesos": "0"}, {"Fecha": "22-05-2023", "Región": "La Araucanía", "Comuna": "LUMACO", "Urbano/Rural": "RURAL", "Calleuno": "Sin especificar", "Calledos": "Sin especificar", "Ubicación/km": "1", "Siniestros": "Volcadura", "Causas": "Velocidad no razonable ni prudente", "Fallecidos": "0", "Graves": "0", "M/Grave": "0", "Leves": "1", "Ilesos": "0"}, {"Fecha": "05-06-2023", "Región": "La Araucanía", "Comuna": "LUMACO", "Urbano/Rural": "RURAL", "Calleuno": "Sin especificar", "Calledos": "Sin especificar", "Ubicación/km": "1", "Siniestros": "Otros", "Causas": "Velocidad no razonable ni prudente", "Fallecidos": "0", "Graves": "0", "M/Grave": "0", "Leves": "0", "Ilesos": "3"}, {"Fecha": "21-11-2023", "Región": "La Araucanía", "Comuna": "LUMACO", "Urbano/Rural": "RURAL", "Calleuno": "Sin especificar", "Calledos": "Sin especificar", "Ubicación/km": "1.5", "Siniestros": "Colisión", "Causas": "Velocidad, no reducir cruce de calles, cumbre, curva,etc.", "Fallecidos": "0", "Graves": "0", "M/Grave": "0", "Leves": "1", "Ilesos": "1"}, {"Fecha": "07-01-2024", "Región": "La Araucanía", "Comuna": "LUMACO", "Urbano/Rural": "Rural", "Calleuno": "Sin especificar", "Calledos": "Sin especificar", "Ubicación/km": "50", "Siniestros": "Colisión", "Causas": "No respetar derecho preferente de paso a vehículo", "Fallecidos": "0", "Graves": "0", "M/Grave": "0", "Leves": "0", "Ilesos": "1"}, {"Fecha": "15-01-2024", "Región": "La Araucanía", "Comuna": "LUMACO", "Urbano/Rural": "Rural", "Calleuno": "Sin especificar", "Calledos": "Sin especificar", "Ubicación/km": "30", "Siniestros": "Volcadura", "Causas": "Conducción no atento condiciones transito momento", "Fallecidos": "0", "Graves": "0", "M/Grave": "0", "Leves": "0", "Ilesos": "1"}, {"Fecha": "16-01-2024", "Región": "La Araucanía", "Comuna": "LUMACO", "Urbano/Rural": "Rural", "Calleuno": "Sin especificar", "Calledos": "Sin especificar", "Ubicación/km": "11", "Siniestros": "Colisión", "Causas": "Conducción no atento condiciones transito momento", "Fallecidos": "0", "Graves": "0", "M/Grave": "0", "Leves": "0", "Ilesos": "2"}, {"Fecha": "25-01-2024", "Región": "La Araucanía", "Comuna": "LUMACO", "Urbano/Rural": "Rural", "Calleuno": "Sin especificar", "Calledos": "Sin especificar", "Ubicación/km": "9", "Siniestros": "Choque", "Causas": "Velocidad no razonable ni prudente", "Fallecidos": "0", "Graves": "0", "M/Grave": "0", "Leves": "0", "Ilesos": "1"}, {"Fecha": "09-05-2024", "Región": "La Araucanía", "Comuna": "LUMACO", "Urbano/Rural": "Rural", "Calleuno": "Sin especificar", "Calledos": "Sin especificar", "Ubicación/km": "5", "Siniestros": "Choque", "Causas": "Conducción no atento condiciones transito momento", "Fallecidos": "0", "Graves": "0", "M/Grave": "0", "Leves": "0", "Ilesos": "1"}, {"Fecha": "09-05-2024", "Región": "La Araucanía", "Comuna": "LUMACO", "Urbano/Rural": "Rural", "Calleuno": "Sin especificar", "Calledos": "Sin especificar", "Ubicación/km": "2.5", "Siniestros": "Otros", "Causas": "Conducción no atento condiciones transito momento", "Fallecidos": "0", "Graves": "0", "M/Grave": "0", "Leves": "0", "Ilesos": "1"}, {"Fecha": "16-05-2024", "Región": "La Araucanía", "Comuna": "LUMACO", "Urbano/Rural": "Rural", "Calleuno": "Sin especificar", "Calledos": "Sin especificar", "Ubicación/km": "30", "Siniestros": "Colisión", "Causas": "Conducción no atento condiciones transito momento", "Fallecidos": "0", "Graves": "0", "M/Grave": "0", "Leves": "0", "Ilesos": "2"}, {"Fecha": "04-06-2024", "Región": "La Araucanía", "Comuna": "LUMACO", "Urbano/Rural": "Rural", "Calleuno": "Sin especificar", "Calledos": "Sin especificar", "Ubicación/km": "18", "Siniestros": "Volcadura", "Causas": "Velocidad, no reducir cruce de calles, cumbre, curva,etc.", "Fallecidos": "0", "Graves": "1", "M/Grave": "0", "Leves": "0", "Ilesos": "0"}, {"Fecha": "12-06-2024", "Región": "La Araucanía", "Comuna": "LUMACO", "Urbano/Rural": "Rural", "Calleuno": "Sin especificar", "Calledos": "Sin especificar", "Ubicación/km": "5", "Siniestros": "Choque", "Causas": "Animales sueltos via publica", "Fallecidos": "0", "Graves": "0", "M/Grave": "0", "Leves": "0", "Ilesos": "4"}, {"Fecha": "25-06-2024", "Región": "La Araucanía", "Comuna": "LUMACO", "Urbano/Rural": "Rural", "Calleuno": "Sin especificar", "Calledos": "Sin especificar", "Ubicación/km": "0.6", "Siniestros": "Choque", "Causas": "Animales sueltos via publica", "Fallecidos": "0", "Graves": "0", "M/Grave": "0", "Leves": "2", "Ilesos": "0"}, {"Fecha": "25-06-2024", "Región": "La Araucanía", "Comuna": "LUMACO", "Urbano/Rural": "Rural", "Calleuno": "Sin especificar", "Calledos": "Sin especificar", "Ubicación/km": "18", "Siniestros": "Volcadura", "Causas": "Velocidad no razonable ni prudente", "Fallecidos": "0", "Graves": "0", "M/Grave": "1", "Leves": "2", "Ilesos": "1"}, {"Fecha": "06-08-2024", "Región": "La Araucanía", "Comuna": "LUMACO", "Urbano/Rural": "Rural", "Calleuno": "Sin especificar", "Calledos": "Sin especificar", "Ubicación/km": "17", "Siniestros": "Choque", "Causas": "Conducción no atento condiciones transito momento", "Fallecidos": "0", "Graves": "0", "M/Grave": "0", "Leves": "0", "Ilesos": "2"}, {"Fecha": "19-08-2024", "Región": "La Araucanía", "Comuna": "LUMACO", "Urbano/Rural": "Rural", "Calleuno": "Sin especificar", "Calledos": "Sin especificar", "Ubicación/km": "4.5", "Siniestros": "Choque", "Causas": "Animales sueltos via publica", "Fallecidos": "0", "Graves": "0", "M/Grave": "0", "Leves": "0", "Ilesos": "2"}, {"Fecha": "25-08-2024", "Región": "La Araucanía", "Comuna": "LUMACO", "Urbano/Rural": "Rural", "Calleuno": "Sin especificar", "Calledos": "Sin especificar", "Ubicación/km": "7.7", "Siniestros": "Volcadura", "Causas": "Fallas mecánicas, frenos", "Fallecidos": "0", "Graves": "3", "M/Grave": "0", "Leves": "0", "Ilesos": "0"}, {"Fecha": "27-08-2024", "Región": "La Araucanía", "Comuna": "LUMACO", "Urbano/Rural": "Rural", "Calleuno": "Sin especificar", "Calledos": "Sin especificar", "Ubicación/km": "36", "Siniestros": "Colisión", "Causas": "Conducción no atento condiciones transito momento", "Fallecidos": "0", "Graves": "0", "M/Grave": "0", "Leves": "0", "Ilesos": "2"}, {"Fecha": "01-10-2024", "Región": "La Araucanía", "Comuna": "LUMACO", "Urbano/Rural": "Rural", "Calleuno": "Sin especificar", "Calledos": "Sin especificar", "Ubicación/km": "4.5", "Siniestros": "Colisión", "Causas": "Conducción no atento condiciones transito momento", "Fallecidos": "0", "Graves": "0", "M/Grave": "0", "Leves": "0", "Ilesos": "2"}, {"Fecha": "13-10-2024", "Región": "La Araucanía", "Comuna": "LUMACO", "Urbano/Rural": "Rural", "Calleuno": "Sin especificar", "Calledos": "Sin especificar", "Ubicación/km": "6", "Siniestros": "Choque", "Causas": "Animales sueltos via publica", "Fallecidos": "0", "Graves": "0", "M/Grave": "0", "Leves": "0", "Ilesos": "1"}], "sin__x__anibal-pinto": [{"Fecha": "17-09-2021", "Región": "La Araucanía", "Comuna": "LUMACO", "Urbano/Rural": "URBANO", "Calleuno": "Anibal Pinto", "Calledos": "Sin especificar", "Ubicación/km": "", "Siniestros": "Atropello", "Causas": "Peatón, cruza calzada forma sorpresiva o descuidada", "Fallecidos": "0", "Graves": "0", "M/Grave": "1", "Leves": "0", "Ilesos": "1"}], "sin__x__arturo-prat": [{"Fecha": "22-03-2025", "Región": "La Araucanía", "Comuna": "LUMACO", "Urbano/Rural": "URBANO", "Calleuno": "Arturo Prat", "Calledos": "Sin especificar", "Ubicación/km": "268", "Siniestros": "VOLCADURA", "Causas": "ANIMALES SUELTOS VIA PUBLICA", "Fallecidos": "0", "Graves": "0", "M/Grave": "0", "Leves": "1", "Ilesos": "0"}, {"Fecha": "05-11-2020", "Región": "La Araucanía", "Comuna": "LUMACO", "Urbano/Rural": "URBANO", "Calleuno": "Arturo Prat", "Calledos": "Sin especificar", "Ubicación/km": "None", "Siniestros": "Atropello", "Causas": "Peatón, cruza calzada forma sorpresiva o descuidada", "Fallecidos": "0", "Graves": "0", "M/Grave": "1", "Leves": "0", "Ilesos": "1"}, {"Fecha": "16-07-2021", "Región": "La Araucanía", "Comuna": "LUMACO", "Urbano/Rural": "URBANO", "Calleuno": "Arturo Prat", "Calledos": "Sin especificar", "Ubicación/km": "", "Siniestros": "Choque", "Causas": "Conducción no atento condiciones transito momento", "Fallecidos": "1", "Graves": "0", "M/Grave": "0", "Leves": "0", "Ilesos": "0"}, {"Fecha": "15-11-2023", "Región": "La Araucanía", "Comuna": "LUMACO", "Urbano/Rural": "URBANO", "Calleuno": "Arturo Prat", "Calledos": "Sin especificar", "Ubicación/km": "None", "Siniestros": "Choque", "Causas": "Conducción no atento condiciones transito momento", "Fallecidos": "0", "Graves": "0", "M/Grave": "0", "Leves": "0", "Ilesos": "1"}, {"Fecha": "30-01-2024", "Región": "La Araucanía", "Comuna": "LUMACO", "Urbano/Rural": "Rural", "Calleuno": "Arturo Prat", "Calledos": "Sin especificar", "Ubicación/km": "None", "Siniestros": "Atropello", "Causas": "Peatón, cruza camino o carretera sin adoptar precauciones", "Fallecidos": "0", "Graves": "0", "M/Grave": "0", "Leves": "1", "Ilesos": "1"}, {"Fecha": "23-03-2024", "Región": "La Araucanía", "Comuna": "LUMACO", "Urbano/Rural": "Urbano", "Calleuno": "Arturo Prat", "Calledos": "Sin especificar", "Ubicación/km": "None", "Siniestros": "Choque", "Causas": "Conducción no atento condiciones transito momento", "Fallecidos": "0", "Graves": "0", "M/Grave": "0", "Leves": "0", "Ilesos": "2"}], "sin__x__balmaceda-esquina-manuel-rodriguez": [{"Fecha": "28-11-2020", "Región": "La Araucanía", "Comuna": "LUMACO", "Urbano/Rural": "URBANO", "Calleuno": "Balmaceda Esquina Manuel Rodriguez", "Calledos": "Sin especificar", "Ubicación/km": "None", "Siniestros": "Colisión", "Causas": "Otras causas", "Fallecidos": "0", "Graves": "0", "M/Grave": "0", "Leves": "0", "Ilesos": "2"}], "sin__x__carlos-condell": [{"Fecha": "07-02-2023", "Región": "La Araucanía", "Comuna": "LUMACO", "Urbano/Rural": "URBANO", "Calleuno": "Carlos Condell", "Calledos": "Sin especificar", "Ubicación/km": "None", "Siniestros": "Choque", "Causas": "Vehiculo en retroceso, conducir", "Fallecidos": "0", "Graves": "0", "M/Grave": "0", "Leves": "0", "Ilesos": "1"}], "sin__x__carlos-condell-esquina-los-carrera": [{"Fecha": "19-08-2022", "Región": "La Araucanía", "Comuna": "LUMACO", "Urbano/Rural": "URBANO", "Calleuno": "Carlos Condell Esquina Los Carrera", "Calledos": "Sin especificar", "Ubicación/km": "None", "Siniestros": "Choque", "Causas": "Conducción no atento condiciones transito momento", "Fallecidos": "0", "Graves": "0", "M/Grave": "0", "Leves": "1", "Ilesos": "1"}], "sin__x__circunvalacion-esquina-dante": [{"Fecha": "21-02-2020", "Región": "La Araucanía", "Comuna": "LUMACO", "Urbano/Rural": "URBANO", "Calleuno": "Circunvalacion Esquina Dante", "Calledos": "Sin especificar", "Ubicación/km": "None", "Siniestros": "Colisión", "Causas": "Adelantamiento sobrepasando línea continua", "Fallecidos": "0", "Graves": "0", "M/Grave": "0", "Leves": "0", "Ilesos": "2"}], "sin__x__dante": [{"Fecha": "18-02-2023", "Región": "La Araucanía", "Comuna": "LUMACO", "Urbano/Rural": "URBANO", "Calleuno": "Dante", "Calledos": "Sin especificar", "Ubicación/km": "None", "Siniestros": "Choque", "Causas": "Vehiculo en retroceso, conducir", "Fallecidos": "0", "Graves": "0", "M/Grave": "0", "Leves": "0", "Ilesos": "2"}], "sin__x__dante-esquina-urrutia": [{"Fecha": "14-06-2022", "Región": "La Araucanía", "Comuna": "LUMACO", "Urbano/Rural": "URBANO", "Calleuno": "Dante Esquina Urrutia", "Calledos": "Sin especificar", "Ubicación/km": "None", "Siniestros": "Colisión", "Causas": "Conducción en estado de ebriedad", "Fallecidos": "0", "Graves": "0", "M/Grave": "0", "Leves": "0", "Ilesos": "2"}], "sin__x__jose-garibaldi-esq-urrutia": [{"Fecha": "11-03-2020", "Región": "La Araucanía", "Comuna": "LUMACO", "Urbano/Rural": "URBANO", "Calleuno": "Jose Garibaldi Esq Urrutia", "Calledos": "Sin especificar", "Ubicación/km": "None", "Siniestros": "Colisión", "Causas": "Conducción no atento condiciones transito momento", "Fallecidos": "0", "Graves": "0", "M/Grave": "0", "Leves": "0", "Ilesos": "2"}], "sin__x__las-perdices": [{"Fecha": "20-08-2021", "Región": "La Araucanía", "Comuna": "LUMACO", "Urbano/Rural": "URBANO", "Calleuno": "Las Perdices", "Calledos": "Sin especificar", "Ubicación/km": "", "Siniestros": "Atropello", "Causas": "Peatón, ebriedad del", "Fallecidos": "0", "Graves": "0", "M/Grave": "0", "Leves": "1", "Ilesos": "1"}], "sin__x__manuel-montt-esq-carlos-condell": [{"Fecha": "19-02-2021", "Región": "La Araucanía", "Comuna": "LUMACO", "Urbano/Rural": "URBANO", "Calleuno": "Manuel Montt Esq Carlos Condell", "Calledos": "Sin especificar", "Ubicación/km": "", "Siniestros": "Colisión", "Causas": "Causas no determinadas", "Fallecidos": "0", "Graves": "0", "M/Grave": "0", "Leves": "0", "Ilesos": "2"}], "sin__x__modena": [{"Fecha": "20-05-2024", "Región": "La Araucanía", "Comuna": "LUMACO", "Urbano/Rural": "Urbano", "Calleuno": "Modena", "Calledos": "Sin especificar", "Ubicación/km": "None", "Siniestros": "Choque", "Causas": "Conducción en estado de ebriedad", "Fallecidos": "0", "Graves": "0", "M/Grave": "0", "Leves": "0", "Ilesos": "2"}], "sin__x__ruta-r-90-p": [{"Fecha": "21-03-2025", "Región": "La Araucanía", "Comuna": "LUMACO", "Urbano/Rural": "RURAL", "Calleuno": "Ruta R 90 P", "Calledos": "Sin especificar", "Ubicación/km": "19", "Siniestros": "CHOQUE", "Causas": "ANIMALES SUELTOS VIA PUBLICA", "Fallecidos": "0", "Graves": "1", "M/Grave": "0", "Leves": "0", "Ilesos": "0"}], "sin__x__ruta-r-s20": [{"Fecha": "25-01-2025", "Región": "La Araucanía", "Comuna": "LUMACO", "Urbano/Rural": "RURAL", "Calleuno": "ruta r720", "Calledos": "Sin especificar", "Ubicación/km": "8", "Siniestros": "COLISION", "Causas": "OTRAS CAUSAS", "Fallecidos": "0", "Graves": "0", "M/Grave": "0", "Leves": "1", "Ilesos": "1"}], "anibal-pinto__x__carlos-condell": [{"Fecha": "22-07-2024", "Región": "La Araucanía", "Comuna": "LUMACO", "Urbano/Rural": "Urbano", "Calleuno": "Anibal Pinto", "Calledos": "Carlos Condell", "Ubicación/km": "None", "Siniestros": "Colisión", "Causas": "Conducción no atento condiciones transito momento", "Fallecidos": "0", "Graves": "0", "M/Grave": "1", "Leves": "0", "Ilesos": "1"}], "balmaceda__x__garibaldi": [{"Fecha": "18-04-2024", "Región": "La Araucanía", "Comuna": "LUMACO", "Urbano/Rural": "Urbano", "Calleuno": "Balmaceda", "Calledos": "Garibaldi", "Ubicación/km": "None", "Siniestros": "Colisión", "Causas": "No respetar derecho preferente de paso a vehículo", "Fallecidos": "0", "Graves": "0", "M/Grave": "0", "Leves": "0", "Ilesos": "2"}], "carlos-condell__x__manuel-montt": [{"Fecha": "20-04-2021", "Región": "La Araucanía", "Comuna": "LUMACO", "Urbano/Rural": "URBANO", "Calleuno": "Manuel Montt", "Calledos": "Carlos Condell", "Ubicación/km": "", "Siniestros": "Choque", "Causas": "Conducción no atento condiciones transito momento", "Fallecidos": "0", "Graves": "0", "M/Grave": "0", "Leves": "0", "Ilesos": "2"}], "caupolican__x__dante": [{"Fecha": "19-09-2021", "Región": "La Araucanía", "Comuna": "LUMACO", "Urbano/Rural": "URBANO", "Calleuno": "Caupolican", "Calledos": "Dante", "Ubicación/km": "", "Siniestros": "Colisión", "Causas": "Conducción en estado de ebriedad", "Fallecidos": "0", "Graves": "0", "M/Grave": "0", "Leves": "0", "Ilesos": "2"}], "cuchibuaso__x__pedro-montt": [{"Fecha": "27-02-2022", "Región": "La Araucanía", "Comuna": "LUMACO", "Urbano/Rural": "URBANO", "Calleuno": "Pedro Montt", "Calledos": "Cuchibuaso", "Ubicación/km": "None", "Siniestros": "Choque", "Causas": "Vehículo en retroceso, conducir", "Fallecidos": "0", "Graves": "0", "M/Grave": "0", "Leves": "0", "Ilesos": "1"}, {"Fecha": "17-02-2023", "Región": "La Araucanía", "Comuna": "LUMACO", "Urbano/Rural": "URBANO", "Calleuno": "Pedro Montt", "Calledos": "Cuchibuaso", "Ubicación/km": "None", "Siniestros": "Choque", "Causas": "Conducción bajo influencia de drogas o estupefacientes", "Fallecidos": "0", "Graves": "1", "M/Grave": "0", "Leves": "0", "Ilesos": "0"}], "ignacio-serrano__x__santa-maria-s": [{"Fecha": "05-12-2023", "Región": "La Araucanía", "Comuna": "LUMACO", "Urbano/Rural": "URBANO", "Calleuno": "Santa Maria S", "Calledos": "Ignacio Serrano", "Ubicación/km": "None", "Siniestros": "Choque", "Causas": "Conducción no atento condiciones transito momento", "Fallecidos": "0", "Graves": "0", "M/Grave": "0", "Leves": "0", "Ilesos": "1"}], "jose-balmaceda__x__jose-garibaldi": [{"Fecha": "04-04-2023", "Región": "La Araucanía", "Comuna": "LUMACO", "Urbano/Rural": "URBANO", "Calleuno": "Jose Garibaldi", "Calledos": "Jose Balmaceda", "Ubicación/km": "None", "Siniestros": "Colisión", "Causas": "Conducción no atento condiciones transito momento", "Fallecidos": "0", "Graves": "0", "M/Grave": "0", "Leves": "0", "Ilesos": "2"}]}}