{"intersections": {"11-de-septiembre__x__cura-cornejo": [{"Fecha": "14-08-2022", "Región": "Libertador General Bernardo O’Higgins", "Comuna": "PUMANQUE", "Urbano/Rural": "URBANO", "Calleuno": "Cura Cornejo", "Calledos": "11 De Septiembre", "Ubicación/km": "None", "Siniestros": "Colisión", "Causas": "No respetar derecho preferente de paso a vehículo", "Fallecidos": "0", "Graves": "0", "M/Grave": "0", "Leves": "6", "Ilesos": "1"}], "sin__x__sin": [{"Fecha": "04-01-2020", "Región": "Libertador General Bernardo O’Higgins", "Comuna": "PUMANQUE", "Urbano/Rural": "RURAL", "Calleuno": "Sin especificar", "Calledos": "Sin especificar", "Ubicación/km": "6.6", "Siniestros": "Colisión", "Causas": "Conducción no atento condiciones transito momento", "Fallecidos": "0", "Graves": "0", "M/Grave": "2", "Leves": "0", "Ilesos": "0"}, {"Fecha": "11-02-2020", "Región": "Libertador General Bernardo O’Higgins", "Comuna": "PUMANQUE", "Urbano/Rural": "RURAL", "Calleuno": "Sin especificar", "Calledos": "Sin especificar", "Ubicación/km": "6.6", "Siniestros": "Colisión", "Causas": "Conducción no atento condiciones transito momento", "Fallecidos": "0", "Graves": "0", "M/Grave": "0", "Leves": "0", "Ilesos": "2"}, {"Fecha": "12-03-2020", "Región": "Libertador General Bernardo O’Higgins", "Comuna": "PUMANQUE", "Urbano/Rural": "RURAL", "Calleuno": "Sin especificar", "Calledos": "Sin especificar", "Ubicación/km": "8", "Siniestros": "Colisión", "Causas": "Conducción no atento condiciones transito momento", "Fallecidos": "0", "Graves": "0", "M/Grave": "0", "Leves": "0", "Ilesos": "2"}, {"Fecha": "11-04-2020", "Región": "Libertador General Bernardo O’Higgins", "Comuna": "PUMANQUE", "Urbano/Rural": "RURAL", "Calleuno": "Sin especificar", "Calledos": "Sin especificar", "Ubicación/km": "21", "Siniestros": "Volcadura", "Causas": "Perdida control vehículo", "Fallecidos": "0", "Graves": "0", "M/Grave": "0", "Leves": "0", "Ilesos": "1"}, {"Fecha": "23-04-2020", "Región": "Libertador General Bernardo O’Higgins", "Comuna": "PUMANQUE", "Urbano/Rural": "RURAL", "Calleuno": "Sin especificar", "Calledos": "Sin especificar", "Ubicación/km": "14", "Siniestros": "Choque", "Causas": "Condiciones físicas deficientes (cansancio, sueño)", "Fallecidos": "0", "Graves": "0", "M/Grave": "0", "Leves": "1", "Ilesos": "0"}, {"Fecha": "23-04-2020", "Región": "Libertador General Bernardo O’Higgins", "Comuna": "PUMANQUE", "Urbano/Rural": "RURAL", "Calleuno": "Sin especificar", "Calledos": "Sin especificar", "Ubicación/km": "2.9", "Siniestros": "Volcadura", "Causas": "Condiciones físicas deficientes (cansancio, sueño)", "Fallecidos": "0", "Graves": "1", "M/Grave": "0", "Leves": "0", "Ilesos": "3"}, {"Fecha": "14-08-2020", "Región": "Libertador General Bernardo O’Higgins", "Comuna": "PUMANQUE", "Urbano/Rural": "URBANO", "Calleuno": "Sin especificar", "Calledos": "Sin especificar", "Ubicación/km": "18.9", "Siniestros": "Colisión", "Causas": "Conducción no atento condiciones transito momento", "Fallecidos": "0", "Graves": "1", "M/Grave": "1", "Leves": "1", "Ilesos": "1"}, {"Fecha": "21-08-2020", "Región": "Libertador General Bernardo O’Higgins", "Comuna": "PUMANQUE", "Urbano/Rural": "RURAL", "Calleuno": "Sin especificar", "Calledos": "Sin especificar", "Ubicación/km": "None", "Siniestros": "Choque", "Causas": "Conducción no atento condiciones transito momento", "Fallecidos": "0", "Graves": "0", "M/Grave": "0", "Leves": "0", "Ilesos": "2"}, {"Fecha": "26-08-2020", "Región": "Libertador General Bernardo O’Higgins", "Comuna": "PUMANQUE", "Urbano/Rural": "RURAL", "Calleuno": "Sin especificar", "Calledos": "Sin especificar", "Ubicación/km": "33.9", "Siniestros": "Volcadura", "Causas": "Perdida control vehículo", "Fallecidos": "0", "Graves": "0", "M/Grave": "0", "Leves": "2", "Ilesos": "0"}, {"Fecha": "18-09-2020", "Región": "Libertador General Bernardo O’Higgins", "Comuna": "PUMANQUE", "Urbano/Rural": "URBANO", "Calleuno": "Sin especificar", "Calledos": "Sin especificar", "Ubicación/km": "2", "Siniestros": "Choque", "Causas": "Conducción en estado de ebriedad", "Fallecidos": "0", "Graves": "0", "M/Grave": "0", "Leves": "2", "Ilesos": "0"}, {"Fecha": "25-09-2020", "Región": "Libertador General Bernardo O’Higgins", "Comuna": "PUMANQUE", "Urbano/Rural": "URBANO", "Calleuno": "Sin especificar", "Calledos": "Sin especificar", "Ubicación/km": "33.9", "Siniestros": "Colisión", "Causas": "Perdida control vehículo", "Fallecidos": "0", "Graves": "0", "M/Grave": "0", "Leves": "2", "Ilesos": "1"}, {"Fecha": "16-12-2020", "Región": "Libertador General Bernardo O’Higgins", "Comuna": "PUMANQUE", "Urbano/Rural": "RURAL", "Calleuno": "Sin especificar", "Calledos": "Sin especificar", "Ubicación/km": "10", "Siniestros": "Choque", "Causas": "Perdida control vehículo", "Fallecidos": "0", "Graves": "0", "M/Grave": "0", "Leves": "1", "Ilesos": "1"}, {"Fecha": "21-12-2020", "Región": "Libertador General Bernardo O’Higgins", "Comuna": "PUMANQUE", "Urbano/Rural": "RURAL", "Calleuno": "Sin especificar", "Calledos": "Sin especificar", "Ubicación/km": "10", "Siniestros": "Colisión", "Causas": "Conducción no atento condiciones transito momento", "Fallecidos": "0", "Graves": "0", "M/Grave": "0", "Leves": "1", "Ilesos": "1"}, {"Fecha": "23-12-2020", "Región": "Libertador General Bernardo O’Higgins", "Comuna": "PUMANQUE", "Urbano/Rural": "URBANO", "Calleuno": "Sin especificar", "Calledos": "Sin especificar", "Ubicación/km": "0.8", "Siniestros": "Choque", "Causas": "Condiciones físicas deficientes (cansancio, sueño)", "Fallecidos": "0", "Graves": "0", "M/Grave": "0", "Leves": "1", "Ilesos": "0"}, {"Fecha": "26-12-2020", "Región": "Libertador General Bernardo O’Higgins", "Comuna": "PUMANQUE", "Urbano/Rural": "RURAL", "Calleuno": "Sin especificar", "Calledos": "Sin especificar", "Ubicación/km": "30", "Siniestros": "Volcadura", "Causas": "Condiciones físicas deficientes (cansancio, sueño)", "Fallecidos": "0", "Graves": "0", "M/Grave": "0", "Leves": "1", "Ilesos": "0"}, {"Fecha": "28-12-2020", "Región": "Libertador General Bernardo O’Higgins", "Comuna": "PUMANQUE", "Urbano/Rural": "URBANO", "Calleuno": "Sin especificar", "Calledos": "Sin especificar", "Ubicación/km": "33.9", "Siniestros": "Colisión", "Causas": "Conducción, cambiar sorpresivamente pista circulación", "Fallecidos": "0", "Graves": "0", "M/Grave": "0", "Leves": "0", "Ilesos": "2"}, {"Fecha": "01-01-2021", "Región": "Libertador General Bernardo O’Higgins", "Comuna": "PUMANQUE", "Urbano/Rural": "RURAL", "Calleuno": "Sin especificar", "Calledos": "Sin especificar", "Ubicación/km": "4.6", "Siniestros": "Volcadura", "Causas": "Perdida control vehículo", "Fallecidos": "0", "Graves": "1", "M/Grave": "0", "Leves": "0", "Ilesos": "0"}, {"Fecha": "25-01-2021", "Región": "Libertador General Bernardo O’Higgins", "Comuna": "PUMANQUE", "Urbano/Rural": "RURAL", "Calleuno": "Sin especificar", "Calledos": "Sin especificar", "Ubicación/km": "20", "Siniestros": "Choque", "Causas": "Condiciones físicas deficientes (cansancio, sueño)", "Fallecidos": "0", "Graves": "0", "M/Grave": "0", "Leves": "0", "Ilesos": "1"}, {"Fecha": "23-02-2021", "Región": "Libertador General Bernardo O’Higgins", "Comuna": "PUMANQUE", "Urbano/Rural": "URBANO", "Calleuno": "Sin especificar", "Calledos": "Sin especificar", "Ubicación/km": "17", "Siniestros": "Choque", "Causas": "Conducción no atento condiciones transito momento", "Fallecidos": "0", "Graves": "0", "M/Grave": "0", "Leves": "0", "Ilesos": "1"}, {"Fecha": "24-02-2021", "Región": "Libertador General Bernardo O’Higgins", "Comuna": "PUMANQUE", "Urbano/Rural": "RURAL", "Calleuno": "Sin especificar", "Calledos": "Sin especificar", "Ubicación/km": "14", "Siniestros": "Colisión", "Causas": "Conducción no atento condiciones transito momento", "Fallecidos": "0", "Graves": "1", "M/Grave": "0", "Leves": "1", "Ilesos": "2"}, {"Fecha": "03-04-2021", "Región": "Libertador General Bernardo O’Higgins", "Comuna": "PUMANQUE", "Urbano/Rural": "RURAL", "Calleuno": "Sin especificar", "Calledos": "Sin especificar", "Ubicación/km": "23.6", "Siniestros": "Choque", "Causas": "Animales sueltos via publica", "Fallecidos": "0", "Graves": "0", "M/Grave": "0", "Leves": "0", "Ilesos": "1"}, {"Fecha": "06-05-2021", "Región": "Libertador General Bernardo O’Higgins", "Comuna": "PUMANQUE", "Urbano/Rural": "URBANO", "Calleuno": "Sin especificar", "Calledos": "Sin especificar", "Ubicación/km": "1.1", "Siniestros": "Colisión", "Causas": "No respetar derecho preferente de paso a vehículo", "Fallecidos": "0", "Graves": "0", "M/Grave": "0", "Leves": "0", "Ilesos": "2"}, {"Fecha": "07-05-2021", "Región": "Libertador General Bernardo O’Higgins", "Comuna": "PUMANQUE", "Urbano/Rural": "RURAL", "Calleuno": "Sin especificar", "Calledos": "Sin especificar", "Ubicación/km": "13", "Siniestros": "Choque", "Causas": "Conducción no atento condiciones transito momento", "Fallecidos": "0", "Graves": "0", "M/Grave": "0", "Leves": "2", "Ilesos": "0"}, {"Fecha": "31-05-2021", "Región": "Libertador General Bernardo O’Higgins", "Comuna": "PUMANQUE", "Urbano/Rural": "RURAL", "Calleuno": "Sin especificar", "Calledos": "Sin especificar", "Ubicación/km": "14.5", "Siniestros": "Colisión", "Causas": "Fallas mecánicas, frenos", "Fallecidos": "0", "Graves": "0", "M/Grave": "0", "Leves": "1", "Ilesos": "1"}, {"Fecha": "02-06-2021", "Región": "Libertador General Bernardo O’Higgins", "Comuna": "PUMANQUE", "Urbano/Rural": "RURAL", "Calleuno": "Sin especificar", "Calledos": "Sin especificar", "Ubicación/km": "15", "Siniestros": "Volcadura", "Causas": "Conducción no atento condiciones transito momento", "Fallecidos": "0", "Graves": "0", "M/Grave": "0", "Leves": "1", "Ilesos": "0"}, {"Fecha": "07-06-2021", "Región": "Libertador General Bernardo O’Higgins", "Comuna": "PUMANQUE", "Urbano/Rural": "RURAL", "Calleuno": "Sin especificar", "Calledos": "Sin especificar", "Ubicación/km": "14.5", "Siniestros": "Volcadura", "Causas": "Perdida control vehículo", "Fallecidos": "0", "Graves": "0", "M/Grave": "0", "Leves": "1", "Ilesos": "1"}, {"Fecha": "03-10-2021", "Región": "Libertador General Bernardo O’Higgins", "Comuna": "PUMANQUE", "Urbano/Rural": "RURAL", "Calleuno": "Sin especificar", "Calledos": "Sin especificar", "Ubicación/km": "14", "Siniestros": "Colisión", "Causas": "Conducción no atento condiciones transito momento", "Fallecidos": "0", "Graves": "0", "M/Grave": "0", "Leves": "0", "Ilesos": "2"}, {"Fecha": "10-10-2021", "Región": "Libertador General Bernardo O’Higgins", "Comuna": "PUMANQUE", "Urbano/Rural": "RURAL", "Calleuno": "Sin especificar", "Calledos": "Sin especificar", "Ubicación/km": "14.6", "Siniestros": "Volcadura", "Causas": "Perdida control vehículo", "Fallecidos": "0", "Graves": "0", "M/Grave": "0", "Leves": "0", "Ilesos": "1"}, {"Fecha": "22-12-2021", "Región": "Libertador General Bernardo O’Higgins", "Comuna": "PUMANQUE", "Urbano/Rural": "RURAL", "Calleuno": "Sin especificar", "Calledos": "Sin especificar", "Ubicación/km": "16.5", "Siniestros": "Volcadura", "Causas": "Perdida control vehículo", "Fallecidos": "0", "Graves": "0", "M/Grave": "0", "Leves": "1", "Ilesos": "0"}, {"Fecha": "04-01-2022", "Región": "Libertador General Bernardo O’Higgins", "Comuna": "PUMANQUE", "Urbano/Rural": "RURAL", "Calleuno": "Sin especificar", "Calledos": "Sin especificar", "Ubicación/km": "13", "Siniestros": "Colisión", "Causas": "Conducción, cambiar sorpresivamente pista circulación", "Fallecidos": "0", "Graves": "0", "M/Grave": "0", "Leves": "0", "Ilesos": "2"}, {"Fecha": "18-01-2022", "Región": "Libertador General Bernardo O’Higgins", "Comuna": "PUMANQUE", "Urbano/Rural": "RURAL", "Calleuno": "Sin especificar", "Calledos": "Sin especificar", "Ubicación/km": "3.6", "Siniestros": "Choque", "Causas": "Conducción en estado de ebriedad", "Fallecidos": "0", "Graves": "0", "M/Grave": "1", "Leves": "0", "Ilesos": "0"}, {"Fecha": "10-02-2022", "Región": "Libertador General Bernardo O’Higgins", "Comuna": "PUMANQUE", "Urbano/Rural": "RURAL", "Calleuno": "Sin especificar", "Calledos": "Sin especificar", "Ubicación/km": "25", "Siniestros": "Colisión", "Causas": "Conducción sin mantener distancia razonable ni prudente", "Fallecidos": "0", "Graves": "0", "M/Grave": "0", "Leves": "1", "Ilesos": "2"}, {"Fecha": "17-02-2022", "Región": "Libertador General Bernardo O’Higgins", "Comuna": "PUMANQUE", "Urbano/Rural": "RURAL", "Calleuno": "Sin especificar", "Calledos": "Sin especificar", "Ubicación/km": "14", "Siniestros": "Colisión", "Causas": "Virajes indebidos", "Fallecidos": "0", "Graves": "0", "M/Grave": "0", "Leves": "1", "Ilesos": "2"}, {"Fecha": "23-02-2022", "Región": "Libertador General Bernardo O’Higgins", "Comuna": "PUMANQUE", "Urbano/Rural": "RURAL", "Calleuno": "Sin especificar", "Calledos": "Sin especificar", "Ubicación/km": "11.5", "Siniestros": "Choque", "Causas": "Conducción no atento condiciones transito momento", "Fallecidos": "0", "Graves": "0", "M/Grave": "0", "Leves": "3", "Ilesos": "0"}, {"Fecha": "08-03-2022", "Región": "Libertador General Bernardo O’Higgins", "Comuna": "PUMANQUE", "Urbano/Rural": "RURAL", "Calleuno": "Sin especificar", "Calledos": "Sin especificar", "Ubicación/km": "14", "Siniestros": "Colisión", "Causas": "Conducción sin mantener distancia razonable ni prudente", "Fallecidos": "0", "Graves": "0", "M/Grave": "0", "Leves": "1", "Ilesos": "2"}, {"Fecha": "13-03-2022", "Región": "Libertador General Bernardo O’Higgins", "Comuna": "PUMANQUE", "Urbano/Rural": "RURAL", "Calleuno": "Sin especificar", "Calledos": "Sin especificar", "Ubicación/km": "11", "Siniestros": "Colisión", "Causas": "Conducción, cambiar sorpresivamente pista circulación", "Fallecidos": "0", "Graves": "3", "M/Grave": "1", "Leves": "2", "Ilesos": "0"}, {"Fecha": "16-03-2022", "Región": "Libertador General Bernardo O’Higgins", "Comuna": "PUMANQUE", "Urbano/Rural": "RURAL", "Calleuno": "Sin especificar", "Calledos": "Sin especificar", "Ubicación/km": "25.5", "Siniestros": "Volcadura", "Causas": "Señalización, desobedecer señal pare", "Fallecidos": "0", "Graves": "0", "M/Grave": "0", "Leves": "0", "Ilesos": "1"}, {"Fecha": "18-03-2022", "Región": "Libertador General Bernardo O’Higgins", "Comuna": "PUMANQUE", "Urbano/Rural": "RURAL", "Calleuno": "Sin especificar", "Calledos": "Sin especificar", "Ubicación/km": "30", "Siniestros": "Colisión", "Causas": "Conducción en estado de ebriedad", "Fallecidos": "0", "Graves": "0", "M/Grave": "0", "Leves": "2", "Ilesos": "0"}, {"Fecha": "19-03-2022", "Región": "Libertador General Bernardo O’Higgins", "Comuna": "PUMANQUE", "Urbano/Rural": "RURAL", "Calleuno": "Sin especificar", "Calledos": "Sin especificar", "Ubicación/km": "14", "Siniestros": "Colisión", "Causas": "Conducción no atento condiciones transito momento", "Fallecidos": "0", "Graves": "1", "M/Grave": "0", "Leves": "0", "Ilesos": "1"}, {"Fecha": "27-03-2022", "Región": "Libertador General Bernardo O’Higgins", "Comuna": "PUMANQUE", "Urbano/Rural": "RURAL", "Calleuno": "Sin especificar", "Calledos": "Sin especificar", "Ubicación/km": "18", "Siniestros": "Volcadura", "Causas": "Conducción en estado de ebriedad", "Fallecidos": "0", "Graves": "0", "M/Grave": "0", "Leves": "0", "Ilesos": "1"}, {"Fecha": "08-04-2022", "Región": "Libertador General Bernardo O’Higgins", "Comuna": "PUMANQUE", "Urbano/Rural": "RURAL", "Calleuno": "Sin especificar", "Calledos": "Sin especificar", "Ubicación/km": "16", "Siniestros": "Choque", "Causas": "Conducción en estado de ebriedad", "Fallecidos": "0", "Graves": "1", "M/Grave": "0", "Leves": "4", "Ilesos": "0"}, {"Fecha": "13-04-2022", "Región": "Libertador General Bernardo O’Higgins", "Comuna": "PUMANQUE", "Urbano/Rural": "RURAL", "Calleuno": "Sin especificar", "Calledos": "Sin especificar", "Ubicación/km": "24.6", "Siniestros": "Colisión", "Causas": "Conducción en estado de ebriedad", "Fallecidos": "0", "Graves": "0", "M/Grave": "0", "Leves": "1", "Ilesos": "1"}, {"Fecha": "05-07-2022", "Región": "Libertador General Bernardo O’Higgins", "Comuna": "PUMANQUE", "Urbano/Rural": "RURAL", "Calleuno": "Sin especificar", "Calledos": "Sin especificar", "Ubicación/km": "22", "Siniestros": "Colisión", "Causas": "Conducción no atento condiciones transito momento", "Fallecidos": "0", "Graves": "0", "M/Grave": "0", "Leves": "1", "Ilesos": "1"}, {"Fecha": "05-08-2022", "Región": "Libertador General Bernardo O’Higgins", "Comuna": "PUMANQUE", "Urbano/Rural": "RURAL", "Calleuno": "Sin especificar", "Calledos": "Sin especificar", "Ubicación/km": "15", "Siniestros": "Colisión", "Causas": "Adelantamiento sin el espacio y tiempo suficiente", "Fallecidos": "0", "Graves": "0", "M/Grave": "0", "Leves": "1", "Ilesos": "2"}, {"Fecha": "20-08-2022", "Región": "Libertador General Bernardo O’Higgins", "Comuna": "PUMANQUE", "Urbano/Rural": "RURAL", "Calleuno": "Sin especificar", "Calledos": "Sin especificar", "Ubicación/km": "28", "Siniestros": "Choque", "Causas": "Conducción en estado de ebriedad", "Fallecidos": "0", "Graves": "0", "M/Grave": "0", "Leves": "0", "Ilesos": "1"}, {"Fecha": "23-08-2022", "Región": "Libertador General Bernardo O’Higgins", "Comuna": "PUMANQUE", "Urbano/Rural": "RURAL", "Calleuno": "Sin especificar", "Calledos": "Sin especificar", "Ubicación/km": "16", "Siniestros": "Choque", "Causas": "Animales sueltos vía publica", "Fallecidos": "0", "Graves": "0", "M/Grave": "0", "Leves": "0", "Ilesos": "1"}, {"Fecha": "03-12-2022", "Región": "Libertador General Bernardo O’Higgins", "Comuna": "PUMANQUE", "Urbano/Rural": "RURAL", "Calleuno": "Sin especificar", "Calledos": "Sin especificar", "Ubicación/km": "18", "Siniestros": "Choque", "Causas": "Perdida control vehículo", "Fallecidos": "0", "Graves": "1", "M/Grave": "0", "Leves": "0", "Ilesos": "0"}, {"Fecha": "08-12-2022", "Región": "Libertador General Bernardo O’Higgins", "Comuna": "PUMANQUE", "Urbano/Rural": "RURAL", "Calleuno": "Sin especificar", "Calledos": "Sin especificar", "Ubicación/km": "37", "Siniestros": "Volcadura", "Causas": "Conducción en estado de ebriedad", "Fallecidos": "0", "Graves": "1", "M/Grave": "0", "Leves": "0", "Ilesos": "0"}, {"Fecha": "07-03-2023", "Región": "Libertador General Bernardo O’Higgins", "Comuna": "PUMANQUE", "Urbano/Rural": "RURAL", "Calleuno": "Sin especificar", "Calledos": "Sin especificar", "Ubicación/km": "13", "Siniestros": "Colisión", "Causas": "Conducción sin mantener distancia razonable ni prudente", "Fallecidos": "0", "Graves": "0", "M/Grave": "0", "Leves": "0", "Ilesos": "2"}, {"Fecha": "14-03-2023", "Región": "Libertador General Bernardo O’Higgins", "Comuna": "PUMANQUE", "Urbano/Rural": "RURAL", "Calleuno": "Sin especificar", "Calledos": "Sin especificar", "Ubicación/km": "5.5", "Siniestros": "Choque", "Causas": "Conducción no atento condiciones transito momento", "Fallecidos": "0", "Graves": "0", "M/Grave": "0", "Leves": "1", "Ilesos": "4"}, {"Fecha": "26-03-2023", "Región": "Libertador General Bernardo O’Higgins", "Comuna": "PUMANQUE", "Urbano/Rural": "RURAL", "Calleuno": "Sin especificar", "Calledos": "Sin especificar", "Ubicación/km": "14", "Siniestros": "Choque", "Causas": "Fallas mecánicas, neumáticos", "Fallecidos": "0", "Graves": "0", "M/Grave": "0", "Leves": "1", "Ilesos": "1"}, {"Fecha": "09-05-2023", "Región": "Libertador General Bernardo O’Higgins", "Comuna": "PUMANQUE", "Urbano/Rural": "RURAL", "Calleuno": "Sin especificar", "Calledos": "Sin especificar", "Ubicación/km": "1.6", "Siniestros": "Choque", "Causas": "Vehiculo en retroceso, conducir", "Fallecidos": "0", "Graves": "0", "M/Grave": "0", "Leves": "0", "Ilesos": "2"}, {"Fecha": "17-06-2023", "Región": "Libertador General Bernardo O’Higgins", "Comuna": "PUMANQUE", "Urbano/Rural": "RURAL", "Calleuno": "Sin especificar", "Calledos": "Sin especificar", "Ubicación/km": "22", "Siniestros": "Choque", "Causas": "Animales sueltos via publica", "Fallecidos": "0", "Graves": "0", "M/Grave": "0", "Leves": "0", "Ilesos": "1"}, {"Fecha": "25-07-2023", "Región": "Libertador General Bernardo O’Higgins", "Comuna": "PUMANQUE", "Urbano/Rural": "RURAL", "Calleuno": "Sin especificar", "Calledos": "Sin especificar", "Ubicación/km": "33", "Siniestros": "Volcadura", "Causas": "Conducción no atento condiciones transito momento", "Fallecidos": "0", "Graves": "1", "M/Grave": "0", "Leves": "1", "Ilesos": "0"}, {"Fecha": "12-08-2023", "Región": "Libertador General Bernardo O’Higgins", "Comuna": "PUMANQUE", "Urbano/Rural": "RURAL", "Calleuno": "Sin especificar", "Calledos": "Sin especificar", "Ubicación/km": "13", "Siniestros": "Choque", "Causas": "Conducción en estado de ebriedad", "Fallecidos": "0", "Graves": "1", "M/Grave": "0", "Leves": "0", "Ilesos": "0"}, {"Fecha": "24-09-2023", "Región": "Libertador General Bernardo O’Higgins", "Comuna": "PUMANQUE", "Urbano/Rural": "RURAL", "Calleuno": "Sin especificar", "Calledos": "Sin especificar", "Ubicación/km": "5", "Siniestros": "Choque", "Causas": "Animales sueltos via publica", "Fallecidos": "0", "Graves": "0", "M/Grave": "0", "Leves": "0", "Ilesos": "1"}, {"Fecha": "20-10-2023", "Región": "Libertador General Bernardo O’Higgins", "Comuna": "PUMANQUE", "Urbano/Rural": "RURAL", "Calleuno": "Sin especificar", "Calledos": "Sin especificar", "Ubicación/km": "5", "Siniestros": "Choque", "Causas": "Velocidad no razonable ni prudente", "Fallecidos": "0", "Graves": "0", "M/Grave": "0", "Leves": "1", "Ilesos": "0"}, {"Fecha": "26-10-2023", "Región": "Libertador General Bernardo O’Higgins", "Comuna": "PUMANQUE", "Urbano/Rural": "RURAL", "Calleuno": "Sin especificar", "Calledos": "Sin especificar", "Ubicación/km": "3", "Siniestros": "Choque", "Causas": "Animales sueltos via publica", "Fallecidos": "0", "Graves": "0", "M/Grave": "0", "Leves": "0", "Ilesos": "1"}, {"Fecha": "11-02-2024", "Región": "Libertador General Bernardo O’Higgins", "Comuna": "PUMANQUE", "Urbano/Rural": "Rural", "Calleuno": "Sin especificar", "Calledos": "Sin especificar", "Ubicación/km": "2", "Siniestros": "Colisión", "Causas": "Señalización, desobedecer señal pare", "Fallecidos": "0", "Graves": "0", "M/Grave": "0", "Leves": "0", "Ilesos": "2"}, {"Fecha": "18-02-2024", "Región": "Libertador General Bernardo O’Higgins", "Comuna": "PUMANQUE", "Urbano/Rural": "Rural", "Calleuno": "Sin especificar", "Calledos": "Sin especificar", "Ubicación/km": "0", "Siniestros": "Colisión", "Causas": "Conducción, cambiar sorpresivamente pista circulación", "Fallecidos": "0", "Graves": "0", "M/Grave": "0", "Leves": "2", "Ilesos": "0"}, {"Fecha": "12-03-2024", "Región": "Libertador General Bernardo O’Higgins", "Comuna": "PUMANQUE", "Urbano/Rural": "Rural", "Calleuno": "Sin especificar", "Calledos": "Sin especificar", "Ubicación/km": "17", "Siniestros": "Colisión", "Causas": "Conducción, cambiar sorpresivamente pista circulación", "Fallecidos": "0", "Graves": "0", "M/Grave": "0", "Leves": "0", "Ilesos": "2"}, {"Fecha": "11-04-2024", "Región": "Libertador General Bernardo O’Higgins", "Comuna": "PUMANQUE", "Urbano/Rural": "Rural", "Calleuno": "Sin especificar", "Calledos": "Sin especificar", "Ubicación/km": "14", "Siniestros": "Volcadura", "Causas": "Velocidad no razonable ni prudente", "Fallecidos": "0", "Graves": "0", "M/Grave": "0", "Leves": "2", "Ilesos": "0"}, {"Fecha": "09-05-2024", "Región": "Libertador General Bernardo O’Higgins", "Comuna": "PUMANQUE", "Urbano/Rural": "Rural", "Calleuno": "Sin especificar", "Calledos": "Sin especificar", "Ubicación/km": "25", "Siniestros": "Volcadura", "Causas": "Conducción no atento condiciones transito momento", "Fallecidos": "0", "Graves": "0", "M/Grave": "0", "Leves": "1", "Ilesos": "1"}, {"Fecha": "14-07-2024", "Región": "Libertador General Bernardo O’Higgins", "Comuna": "PUMANQUE", "Urbano/Rural": "Rural", "Calleuno": "Sin especificar", "Calledos": "Sin especificar", "Ubicación/km": "12", "Siniestros": "Choque", "Causas": "Conducción en estado de ebriedad", "Fallecidos": "0", "Graves": "1", "M/Grave": "0", "Leves": "2", "Ilesos": "0"}, {"Fecha": "08-08-2024", "Región": "Libertador General Bernardo O’Higgins", "Comuna": "PUMANQUE", "Urbano/Rural": "Rural", "Calleuno": "Sin especificar", "Calledos": "Sin especificar", "Ubicación/km": "14", "Siniestros": "Colisión", "Causas": "Conducción, cambiar sorpresivamente pista circulación", "Fallecidos": "0", "Graves": "0", "M/Grave": "0", "Leves": "0", "Ilesos": "2"}, {"Fecha": "04-12-2024", "Región": "Libertador General Bernardo O’Higgins", "Comuna": "PUMANQUE", "Urbano/Rural": "Rural", "Calleuno": "Sin especificar", "Calledos": "Sin especificar", "Ubicación/km": "23", "Siniestros": "Colisión", "Causas": "Conducción no atento condiciones transito momento", "Fallecidos": "0", "Graves": "0", "M/Grave": "0", "Leves": "0", "Ilesos": "2"}], "sin__x__cementerio": [{"Fecha": "19-06-2023", "Región": "Libertador General Bernardo O’Higgins", "Comuna": "PUMANQUE", "Urbano/Rural": "URBANO", "Calleuno": "Cementerio", "Calledos": "Sin especificar", "Ubicación/km": "None", "Siniestros": "Atropello", "Causas": "Conducción no atento condiciones transito momento", "Fallecidos": "0", "Graves": "1", "M/Grave": "0", "Leves": "0", "Ilesos": "1"}], "sin__x__la-queseria": [{"Fecha": "13-03-2023", "Región": "Libertador General Bernardo O’Higgins", "Comuna": "PUMANQUE", "Urbano/Rural": "URBANO", "Calleuno": "La Queseria", "Calledos": "Sin especificar", "Ubicación/km": "None", "Siniestros": "Choque", "Causas": "Conducción no atento condiciones transito momento", "Fallecidos": "0", "Graves": "0", "M/Grave": "0", "Leves": "0", "Ilesos": "2"}], "sin__x__poblacion-los-jazmines": [{"Fecha": "08-03-2020", "Región": "Libertador General Bernardo O’Higgins", "Comuna": "PUMANQUE", "Urbano/Rural": "URBANO", "Calleuno": "Poblacion Los Jazmines", "Calledos": "Sin especificar", "Ubicación/km": "None", "Siniestros": "Volcadura", "Causas": "Conducción en estado de ebriedad", "Fallecidos": "0", "Graves": "1", "M/Grave": "0", "Leves": "0", "Ilesos": "0"}], "sin__x__publico-sector-la-mina-pumanque": [{"Fecha": "07-07-2022", "Región": "Libertador General Bernardo O’Higgins", "Comuna": "PUMANQUE", "Urbano/Rural": "RURAL", "Calleuno": "Camino a Publico Sector La Mina Pumanque", "Calledos": "Sin especificar", "Ubicación/km": "None", "Siniestros": "Choque", "Causas": "Conducción en estado de ebriedad", "Fallecidos": "0", "Graves": "0", "M/Grave": "0", "Leves": "0", "Ilesos": "1"}], "sin__x__ruta-i": [{"Fecha": "05-02-2025", "Región": "Libertador General Bernardo O’Higgins", "Comuna": "PUMANQUE", "Urbano/Rural": "RURAL", "Calleuno": "ruta i60", "Calledos": "Sin especificar", "Ubicación/km": "10", "Siniestros": "VOLCADURA", "Causas": "CONDUCTOR EN ESTADO DE EBRIEDAD", "Fallecidos": "0", "Graves": "1", "M/Grave": "0", "Leves": "1", "Ilesos": "0"}, {"Fecha": "04-03-2025", "Región": "Libertador General Bernardo O’Higgins", "Comuna": "PUMANQUE", "Urbano/Rural": "URBANO", "Calleuno": "ruta i602", "Calledos": "Sin especificar", "Ubicación/km": "3", "Siniestros": "VOLCADURA", "Causas": "CONDUCTOR NO ATENTO CONDICIONES TRANSITO MOMENTO", "Fallecidos": "0", "Graves": "1", "M/Grave": "0", "Leves": "2", "Ilesos": "0"}, {"Fecha": "10-06-2025", "Región": "Libertador General Bernardo O’Higgins", "Comuna": "PUMANQUE", "Urbano/Rural": "RURAL", "Calleuno": "ruta i60", "Calledos": "Sin especificar", "Ubicación/km": "14", "Siniestros": "COLISION POR ALCANCE", "Causas": "CONDUCTOR NO ATENTO CONDICIONES TRANSITO MOMENTO", "Fallecidos": "0", "Graves": "0", "M/Grave": "0", "Leves": "1", "Ilesos": "1"}, {"Fecha": "24-07-2025", "Región": "Libertador General Bernardo O’Higgins", "Comuna": "PUMANQUE", "Urbano/Rural": "RURAL", "Calleuno": "ruta i60", "Calledos": "Sin especificar", "Ubicación/km": "14", "Siniestros": "COLISION LATERAL", "Causas": "CONDUCTOR CAMBIA SORPRESIVAMENTE PISTA CIRCULACION", "Fallecidos": "0", "Graves": "0", "M/Grave": "0", "Leves": "3", "Ilesos": "0"}, {"Fecha": "19-08-2025", "Región": "Libertador General Bernardo O’Higgins", "Comuna": "PUMANQUE", "Urbano/Rural": "RURAL", "Calleuno": "ruta i60", "Calledos": "Sin especificar", "Ubicación/km": "16", "Siniestros": "CHOQUE FRONTAL", "Causas": "CONDUCTOR NO ATENTO CONDICIONES TRANSITO MOMENTO", "Fallecidos": "0", "Graves": "0", "M/Grave": "0", "Leves": "1", "Ilesos": "0"}, {"Fecha": "28-08-2025", "Región": "Libertador General Bernardo O’Higgins", "Comuna": "PUMANQUE", "Urbano/Rural": "RURAL", "Calleuno": "ruta i60", "Calledos": "Sin especificar", "Ubicación/km": "14", "Siniestros": "CHOQUE FRONTAL", "Causas": "CONDUCTOR NO ATENTO CONDICIONES TRANSITO MOMENTO", "Fallecidos": "0", "Graves": "0", "M/Grave": "0", "Leves": "2", "Ilesos": "0"}], "sin__x__ruta-i-h50": [{"Fecha": "05-08-2025", "Región": "Libertador General Bernardo O’Higgins", "Comuna": "PUMANQUE", "Urbano/Rural": "RURAL", "Calleuno": "ruta i650", "Calledos": "Sin especificar", "Ubicación/km": "7", "Siniestros": "VOLCADURA", "Causas": "CONDUCTOR BAJO LA INFLUENCIA DEL ALCOHOL", "Fallecidos": "0", "Graves": "0", "M/Grave": "0", "Leves": "1", "Ilesos": "0"}], "sin__x__san-pablo-sin-numero": [{"Fecha": "20-02-2021", "Región": "Libertador General Bernardo O’Higgins", "Comuna": "PUMANQUE", "Urbano/Rural": "URBANO", "Calleuno": "San Pablo Sin Numero", "Calledos": "Sin especificar", "Ubicación/km": "", "Siniestros": "Choque", "Causas": "Otras causas", "Fallecidos": "0", "Graves": "0", "M/Grave": "0", "Leves": "0", "Ilesos": "1"}], "sin__x__sector-ranquihue": [{"Fecha": "12-04-2024", "Región": "Libertador General Bernardo O’Higgins", "Comuna": "PUMANQUE", "Urbano/Rural": "Urbano", "Calleuno": "Sector Ranquihue", "Calledos": "Sin especificar", "Ubicación/km": "None", "Siniestros": "Choque", "Causas": "Conducción no atento condiciones transito momento", "Fallecidos": "0", "Graves": "0", "M/Grave": "0", "Leves": "2", "Ilesos": "0"}], "bernardo-o-higgins__x__el-rosario": [{"Fecha": "11-08-2020", "Región": "Libertador General Bernardo O’Higgins", "Comuna": "PUMANQUE", "Urbano/Rural": "URBANO", "Calleuno": "El Rosario", "Calledos": "Bernardo O Higgins", "Ubicación/km": "None", "Siniestros": "Choque", "Causas": "Conducción no atento condiciones transito momento", "Fallecidos": "0", "Graves": "0", "M/Grave": "0", "Leves": "0", "Ilesos": "2"}], "bernardo-o-higgins__x__manuel-rodriguez": [{"Fecha": "10-05-2024", "Región": "Libertador General Bernardo O’Higgins", "Comuna": "PUMANQUE", "Urbano/Rural": "Urbano", "Calleuno": "Manuel Rodriguez", "Calledos": "Bernardo O Higgins", "Ubicación/km": "None", "Siniestros": "Colisión", "Causas": "Adelantamiento sin el espacio y tiempo suficiente", "Fallecidos": "0", "Graves": "0", "M/Grave": "0", "Leves": "0", "Ilesos": "2"}], "calles-los-tilos-sector-rincon-las-ovejas-s__x__n": [{"Fecha": "25-09-2021", "Región": "Libertador General Bernardo O’Higgins", "Comuna": "PUMANQUE", "Urbano/Rural": "RURAL", "Calleuno": "Calles Los Tilos Sector Rincon Las Ovejas S", "Calledos": "N", "Ubicación/km": "", "Siniestros": "Choque", "Causas": "Conducción en estado de ebriedad", "Fallecidos": "0", "Graves": "0", "M/Grave": "0", "Leves": "0", "Ilesos": "1"}], "el-rosario__x__luis-barahona": [{"Fecha": "02-04-2024", "Región": "Libertador General Bernardo O’Higgins", "Comuna": "PUMANQUE", "Urbano/Rural": "Urbano", "Calleuno": "El Rosario", "Calledos": "Luis Barahona", "Ubicación/km": "None", "Siniestros": "Choque", "Causas": "Virajes indebidos", "Fallecidos": "0", "Graves": "0", "M/Grave": "0", "Leves": "0", "Ilesos": "1"}], "el-rosario-s__x__n": [{"Fecha": "31-05-2021", "Región": "Libertador General Bernardo O’Higgins", "Comuna": "PUMANQUE", "Urbano/Rural": "URBANO", "Calleuno": "El Rosario S", "Calledos": "N", "Ubicación/km": "", "Siniestros": "Volcadura", "Causas": "Conducción en estado de ebriedad", "Fallecidos": "0", "Graves": "0", "M/Grave": "0", "Leves": "0", "Ilesos": "1"}], "n__x__publico-santa-teresa-s": [{"Fecha": "13-03-2020", "Región": "Libertador General Bernardo O’Higgins", "Comuna": "PUMANQUE", "Urbano/Rural": "URBANO", "Calleuno": "Camino a Publico Santa Teresa S", "Calledos": "N", "Ubicación/km": "None", "Siniestros": "Choque", "Causas": "Perdida control vehículo", "Fallecidos": "0", "Graves": "0", "M/Grave": "0", "Leves": "0", "Ilesos": "1"}], "n__x__publico-sector-el-sauce-s": [{"Fecha": "01-12-2020", "Región": "Libertador General Bernardo O’Higgins", "Comuna": "PUMANQUE", "Urbano/Rural": "RURAL", "Calleuno": "Camino a Publico Sector El Sauce S", "Calledos": "N", "Ubicación/km": "None", "Siniestros": "Colisión", "Causas": "Conducción no atento condiciones transito momento", "Fallecidos": "0", "Graves": "0", "M/Grave": "0", "Leves": "0", "Ilesos": "2"}], "n__x__publico-sector-la-gloria-s": [{"Fecha": "05-12-2020", "Región": "Libertador General Bernardo O’Higgins", "Comuna": "PUMANQUE", "Urbano/Rural": "RURAL", "Calleuno": "Camino a Publico Sector La Gloria S", "Calledos": "N", "Ubicación/km": "None", "Siniestros": "Colisión", "Causas": "Conducción, cambiar sorpresivamente pista circulación", "Fallecidos": "0", "Graves": "0", "M/Grave": "0", "Leves": "1", "Ilesos": "1"}], "n__x__publico-sector-ranquilhue-s": [{"Fecha": "09-04-2022", "Región": "Libertador General Bernardo O’Higgins", "Comuna": "PUMANQUE", "Urbano/Rural": "RURAL", "Calleuno": "Camino a Publico Sector Ranquilhue S", "Calledos": "N", "Ubicación/km": "None", "Siniestros": "Colisión", "Causas": "Conducción, cambiar sorpresivamente pista circulación", "Fallecidos": "0", "Graves": "0", "M/Grave": "0", "Leves": "0", "Ilesos": "2"}], "padre-vasquez__x__rosario": [{"Fecha": "19-10-2021", "Región": "Libertador General Bernardo O’Higgins", "Comuna": "PUMANQUE", "Urbano/Rural": "URBANO", "Calleuno": "Padre Vasquez", "Calledos": "Rosario", "Ubicación/km": "", "Siniestros": "Colisión", "Causas": "No respetar derecho preferente de paso a vehículo", "Fallecidos": "0", "Graves": "1", "M/Grave": "0", "Leves": "0", "Ilesos": "1"}], "san-pablo__x__santa-clotilde": [{"Fecha": "02-02-2023", "Región": "Libertador General Bernardo O’Higgins", "Comuna": "PUMANQUE", "Urbano/Rural": "URBANO", "Calleuno": "Santa Clotilde", "Calledos": "San Pablo", "Ubicación/km": "None", "Siniestros": "Colisión", "Causas": "Adelantamiento en cruce, curva, cuesta, puente", "Fallecidos": "0", "Graves": "0", "M/Grave": "0", "Leves": "1", "Ilesos": "1"}]}}