{"intersections": {"abraham-ahumada__x__tres-carrera": [{"Fecha": "25-04-2023", "Región": "Valparaíso", "Comuna": "SANTA MARIA", "Urbano/Rural": "URBANO", "Calleuno": "Tres Carrera", "Calledos": "Abraham Ahumada", "Ubicación/km": "None", "Siniestros": "Colisión", "Causas": "Conducción no atento condiciones transito momento", "Fallecidos": "0", "Graves": "0", "M/Grave": "0", "Leves": "0", "Ilesos": "2"}], "agustin-edwards__x__jose-miguel-carrera": [{"Fecha": "23-11-2023", "Región": "Valparaíso", "Comuna": "SANTA MARIA", "Urbano/Rural": "URBANO", "Calleuno": "Gran Avenida José Miguel Carrera", "Calledos": "Agustin Edwards", "Ubicación/km": "None", "Siniestros": "Colisión", "Causas": "Señalización, desobedecer señal pare", "Fallecidos": "0", "Graves": "0", "M/Grave": "0", "Leves": "1", "Ilesos": "1"}], "almendral__x__guillisasty": [{"Fecha": "01-07-2021", "Región": "Valparaíso", "Comuna": "SANTA MARIA", "Urbano/Rural": "RURAL", "Calleuno": "Almendral", "Calledos": "Guillisasty", "Ubicación/km": "", "Siniestros": "Colisión", "Causas": "Señalización, desobedecer señal pare", "Fallecidos": "0", "Graves": "0", "M/Grave": "0", "Leves": "1", "Ilesos": "1"}], "almendral__x__piedra-el-leon": [{"Fecha": "02-05-2023", "Región": "Valparaíso", "Comuna": "SANTA MARIA", "Urbano/Rural": "URBANO", "Calleuno": "Almendral", "Calledos": "Piedra El Leon", "Ubicación/km": "None", "Siniestros": "Choque", "Causas": "Animales sueltos via publica", "Fallecidos": "0", "Graves": "0", "M/Grave": "0", "Leves": "0", "Ilesos": "1"}], "almirante-latorre__x__ignacio-carrera-pinto": [{"Fecha": "18-06-2025", "Región": "Valparaíso", "Comuna": "SANTA MARIA", "Urbano/Rural": "URBANO", "Calleuno": "Almirante Latorre", "Calledos": "Ignacio Carrera Pinto", "Ubicación/km": "None", "Siniestros": "COLISION", "Causas": "CONDUCTOR NO ATENTO CONDICIONES TRANSITO MOMENTO", "Fallecidos": "0", "Graves": "0", "M/Grave": "0", "Leves": "1", "Ilesos": "1"}], "almirante-latorre__x__irarrazaval": [{"Fecha": "27-11-2020", "Región": "Valparaíso", "Comuna": "SANTA MARIA", "Urbano/Rural": "URBANO", "Calleuno": "Almirante Latorre", "Calledos": "Irarrazaval", "Ubicación/km": "None", "Siniestros": "Colisión", "Causas": "Otras causas", "Fallecidos": "1", "Graves": "0", "M/Grave": "0", "Leves": "0", "Ilesos": "1"}], "almirante-latorre__x__palmeras": [{"Fecha": "15-11-2021", "Región": "Valparaíso", "Comuna": "SANTA MARIA", "Urbano/Rural": "URBANO", "Calleuno": "Almirante Latorre", "Calledos": "Palmeras", "Ubicación/km": "", "Siniestros": "Colisión", "Causas": "Conducción no atento condiciones transito momento", "Fallecidos": "0", "Graves": "0", "M/Grave": "0", "Leves": "1", "Ilesos": "1"}], "almirante-latorre__x__pehuen": [{"Fecha": "30-05-2021", "Región": "Valparaíso", "Comuna": "SANTA MARIA", "Urbano/Rural": "URBANO", "Calleuno": "Pehuen", "Calledos": "Almirante Latorre", "Ubicación/km": "", "Siniestros": "Atropello", "Causas": "Señalización, desobedecer luz roja de semáforo", "Fallecidos": "0", "Graves": "0", "M/Grave": "1", "Leves": "0", "Ilesos": "2"}], "almirante-latorre__x__san-fernando": [{"Fecha": "10-01-2020", "Región": "Valparaíso", "Comuna": "SANTA MARIA", "Urbano/Rural": "URBANO", "Calleuno": "San Fernando", "Calledos": "Almirante Latorre", "Ubicación/km": "None", "Siniestros": "Colisión", "Causas": "Conducción no atento condiciones transito momento", "Fallecidos": "0", "Graves": "0", "M/Grave": "0", "Leves": "1", "Ilesos": "1"}], "almirante-latorre__x__san-jose": [{"Fecha": "04-04-2025", "Región": "Valparaíso", "Comuna": "SANTA MARIA", "Urbano/Rural": "RURAL", "Calleuno": "San Jose", "Calledos": "Almirante Latorre", "Ubicación/km": "None", "Siniestros": "COLISION", "Causas": "CONDUCTOR NO ATENTO CONDICIONES TRANSITO MOMENTO", "Fallecidos": "0", "Graves": "0", "M/Grave": "0", "Leves": "0", "Ilesos": "2"}], "amancay__x__el-canelo": [{"Fecha": "28-11-2021", "Región": "Valparaíso", "Comuna": "SANTA MARIA", "Urbano/Rural": "URBANO", "Calleuno": "Amancay", "Calledos": "El Canelo", "Ubicación/km": "", "Siniestros": "Choque", "Causas": "Perdida control vehículo", "Fallecidos": "0", "Graves": "0", "M/Grave": "0", "Leves": "0", "Ilesos": "1"}], "ancha__x__autonomia": [{"Fecha": "23-03-2022", "Región": "Valparaíso", "Comuna": "SANTA MARIA", "Urbano/Rural": "URBANO", "Calleuno": "Ancha", "Calledos": "Autonomia", "Ubicación/km": "None", "Siniestros": "Colisión", "Causas": "Señalización, desobedecer señal pare", "Fallecidos": "0", "Graves": "0", "M/Grave": "0", "Leves": "2", "Ilesos": "0"}, {"Fecha": "03-05-2023", "Región": "Valparaíso", "Comuna": "SANTA MARIA", "Urbano/Rural": "URBANO", "Calleuno": "Autonomia", "Calledos": "Ancha", "Ubicación/km": "None", "Siniestros": "Colisión", "Causas": "Conducción, cambiar sorpresivamente pista circulación", "Fallecidos": "0", "Graves": "0", "M/Grave": "2", "Leves": "1", "Ilesos": "0"}], "autonomia__x__condominio-guingan": [{"Fecha": "15-03-2024", "Región": "Valparaíso", "Comuna": "SANTA MARIA", "Urbano/Rural": "Urbano", "Calleuno": "Condominio Guingan", "Calledos": "Autonomia", "Ubicación/km": "None", "Siniestros": "Colisión", "Causas": "Conducción no atento condiciones transito momento", "Fallecidos": "0", "Graves": "1", "M/Grave": "0", "Leves": "0", "Ilesos": "1"}], "autonomia__x__irarrazabal": [{"Fecha": "18-01-2020", "Región": "Valparaíso", "Comuna": "SANTA MARIA", "Urbano/Rural": "RURAL", "Calleuno": "Autonomia", "Calledos": "Irarrazabal", "Ubicación/km": "None", "Siniestros": "Choque", "Causas": "Perdida control vehículo", "Fallecidos": "0", "Graves": "0", "M/Grave": "0", "Leves": "0", "Ilesos": "1"}], "autonomia__x__uribe": [{"Fecha": "15-08-2024", "Región": "Valparaíso", "Comuna": "SANTA MARIA", "Urbano/Rural": "Urbano", "Calleuno": "Uribe", "Calledos": "Autonomia", "Ubicación/km": "None", "Siniestros": "Choque", "Causas": "Fallas mecánicas, neumáticos", "Fallecidos": "0", "Graves": "0", "M/Grave": "0", "Leves": "0", "Ilesos": "1"}], "benito-larranaga__x__latorre": [{"Fecha": "31-10-2021", "Región": "Valparaíso", "Comuna": "SANTA MARIA", "Urbano/Rural": "URBANO", "Calleuno": "Latorre", "Calledos": "Benito Larranaga", "Ubicación/km": "", "Siniestros": "Atropello", "Causas": "Peatón, cruza calzada forma sorpresiva o descuidada", "Fallecidos": "0", "Graves": "0", "M/Grave": "0", "Leves": "1", "Ilesos": "1"}], "bernardo-o-higgins__x__irarrazabal": [{"Fecha": "18-01-2020", "Región": "Valparaíso", "Comuna": "SANTA MARIA", "Urbano/Rural": "URBANO", "Calleuno": "Bernardo O Higgins", "Calledos": "Irarrazabal", "Ubicación/km": "None", "Siniestros": "Colisión", "Causas": "Conducción no atento condiciones transito momento", "Fallecidos": "0", "Graves": "0", "M/Grave": "0", "Leves": "2", "Ilesos": "0"}, {"Fecha": "19-05-2023", "Región": "Valparaíso", "Comuna": "SANTA MARIA", "Urbano/Rural": "URBANO", "Calleuno": "Bernardo O Higgins", "Calledos": "Irarrazabal", "Ubicación/km": "None", "Siniestros": "Colisión", "Causas": "Conducción no atento condiciones transito momento", "Fallecidos": "0", "Graves": "0", "M/Grave": "0", "Leves": "0", "Ilesos": "2"}], "bernardo-o-higgins__x__irarrazaval": [{"Fecha": "02-02-2020", "Región": "Valparaíso", "Comuna": "SANTA MARIA", "Urbano/Rural": "URBANO", "Calleuno": "Bernardo O Higgins", "Calledos": "Irarrazaval", "Ubicación/km": "None", "Siniestros": "Colisión", "Causas": "Señalización, desobedecer luz roja de semáforo", "Fallecidos": "0", "Graves": "1", "M/Grave": "0", "Leves": "0", "Ilesos": "1"}, {"Fecha": "19-03-2020", "Región": "Valparaíso", "Comuna": "SANTA MARIA", "Urbano/Rural": "URBANO", "Calleuno": "Bernardo O Higgins", "Calledos": "Irarrazaval", "Ubicación/km": "None", "Siniestros": "Colisión", "Causas": "Conducción no atento condiciones transito momento", "Fallecidos": "0", "Graves": "0", "M/Grave": "0", "Leves": "0", "Ilesos": "2"}, {"Fecha": "25-01-2021", "Región": "Valparaíso", "Comuna": "SANTA MARIA", "Urbano/Rural": "URBANO", "Calleuno": "Bernardo O Higgins", "Calledos": "Irarrazaval", "Ubicación/km": "", "Siniestros": "Colisión", "Causas": "Conducción no atento condiciones transito momento", "Fallecidos": "0", "Graves": "0", "M/Grave": "0", "Leves": "2", "Ilesos": "1"}, {"Fecha": "03-06-2022", "Región": "Valparaíso", "Comuna": "SANTA MARIA", "Urbano/Rural": "URBANO", "Calleuno": "Bernardo O Higgins", "Calledos": "Irarrazaval", "Ubicación/km": "None", "Siniestros": "Choque", "Causas": "Conducción bajo la influencia del alcohol", "Fallecidos": "0", "Graves": "0", "M/Grave": "0", "Leves": "0", "Ilesos": "2"}, {"Fecha": "24-11-2022", "Región": "Valparaíso", "Comuna": "SANTA MARIA", "Urbano/Rural": "URBANO", "Calleuno": "Irarrazaval", "Calledos": "Bernardo O Higgins", "Ubicación/km": "None", "Siniestros": "Colisión", "Causas": "Señalización, desobedecer luz roja de semáforo", "Fallecidos": "0", "Graves": "0", "M/Grave": "0", "Leves": "2", "Ilesos": "0"}, {"Fecha": "12-04-2024", "Región": "Valparaíso", "Comuna": "SANTA MARIA", "Urbano/Rural": "Urbano", "Calleuno": "Bernardo O Higgins", "Calledos": "Irarrazaval", "Ubicación/km": "None", "Siniestros": "Choque", "Causas": "Conducción no atento condiciones transito momento", "Fallecidos": "0", "Graves": "0", "M/Grave": "0", "Leves": "0", "Ilesos": "1"}, {"Fecha": "12-12-2024", "Región": "Valparaíso", "Comuna": "SANTA MARIA", "Urbano/Rural": "Urbano", "Calleuno": "Bernardo O Higgins", "Calledos": "Irarrazaval", "Ubicación/km": "None", "Siniestros": "Colisión", "Causas": "Conducción no atento condiciones transito momento", "Fallecidos": "0", "Graves": "0", "M/Grave": "0", "Leves": "0", "Ilesos": "2"}], "bernardo-o-higgins__x__manuel-rodriguez": [{"Fecha": "19-03-2021", "Región": "Valparaíso", "Comuna": "SANTA MARIA", "Urbano/Rural": "URBANO", "Calleuno": "Bernardo O Higgins", "Calledos": "Manuel Rodriguez", "Ubicación/km": "", "Siniestros": "Colisión", "Causas": "Señalización, desobedecer señal pare", "Fallecidos": "0", "Graves": "0", "M/Grave": "0", "Leves": "4", "Ilesos": "0"}, {"Fecha": "03-05-2021", "Región": "Valparaíso", "Comuna": "SANTA MARIA", "Urbano/Rural": "URBANO", "Calleuno": "Manuel Rodriguez", "Calledos": "Bernardo O Higgins", "Ubicación/km": "", "Siniestros": "Colisión", "Causas": "Señalización, desobedecer señal pare", "Fallecidos": "0", "Graves": "0", "M/Grave": "0", "Leves": "2", "Ilesos": "0"}, {"Fecha": "23-05-2022", "Región": "Valparaíso", "Comuna": "SANTA MARIA", "Urbano/Rural": "URBANO", "Calleuno": "Bernardo O Higgins", "Calledos": "Manuel Rodriguez", "Ubicación/km": "None", "Siniestros": "Colisión", "Causas": "Conducción no atento condiciones transito momento", "Fallecidos": "0", "Graves": "0", "M/Grave": "0", "Leves": "1", "Ilesos": "1"}], "bernardo-o-higgins__x__octavio-lazcano": [{"Fecha": "09-07-2020", "Región": "Valparaíso", "Comuna": "SANTA MARIA", "Urbano/Rural": "RURAL", "Calleuno": "Bernardo O Higgins", "Calledos": "Octavio Lazcano", "Ubicación/km": "None", "Siniestros": "Volcadura", "Causas": "Perdida control vehículo", "Fallecidos": "0", "Graves": "0", "M/Grave": "0", "Leves": "2", "Ilesos": "0"}], "bernardo-o-higgins__x__tres-carrera": [{"Fecha": "02-09-2022", "Región": "Valparaíso", "Comuna": "SANTA MARIA", "Urbano/Rural": "URBANO", "Calleuno": "Bernardo O Higgins", "Calledos": "Tres Carrera", "Ubicación/km": "None", "Siniestros": "Atropello", "Causas": "No respetar derecho preferente de paso a peatón", "Fallecidos": "0", "Graves": "0", "M/Grave": "0", "Leves": "1", "Ilesos": "1"}], "canto__x__el-medio": [{"Fecha": "05-08-2024", "Región": "Valparaíso", "Comuna": "SANTA MARIA", "Urbano/Rural": "Rural", "Calleuno": "Canto", "Calledos": "El Medio", "Ubicación/km": "None", "Siniestros": "Colisión", "Causas": "Señalización, desobedecer señal pare", "Fallecidos": "0", "Graves": "0", "M/Grave": "0", "Leves": "1", "Ilesos": "2"}], "canto__x__placilla": [{"Fecha": "26-11-2023", "Región": "Valparaíso", "Comuna": "SANTA MARIA", "Urbano/Rural": "URBANO", "Calleuno": "Canto", "Calledos": "Placilla", "Ubicación/km": "None", "Siniestros": "Volcadura", "Causas": "Velocidad no razonable ni prudente", "Fallecidos": "0", "Graves": "2", "M/Grave": "0", "Leves": "1", "Ilesos": "0"}], "carlos-zuniga__x__ignacio-carrera-pinto": [{"Fecha": "20-02-2023", "Región": "Valparaíso", "Comuna": "SANTA MARIA", "Urbano/Rural": "URBANO", "Calleuno": "Ignacio Carrera Pinto", "Calledos": "Carlos Zuniga", "Ubicación/km": "None", "Siniestros": "Colisión", "Causas": "Señalización, desobedecer luz roja de semáforo", "Fallecidos": "0", "Graves": "0", "M/Grave": "0", "Leves": "2", "Ilesos": "0"}], "carlos-zuniga__x__las-encinas": [{"Fecha": "28-08-2023", "Región": "Valparaíso", "Comuna": "SANTA MARIA", "Urbano/Rural": "URBANO", "Calleuno": "Carlos Zuniga", "Calledos": "Las Encinas", "Ubicación/km": "None", "Siniestros": "Choque", "Causas": "Conducción no atento condiciones transito momento", "Fallecidos": "0", "Graves": "0", "M/Grave": "0", "Leves": "0", "Ilesos": "1"}], "carlos-zuniga__x__los-boldos": [{"Fecha": "09-06-2024", "Región": "Valparaíso", "Comuna": "SANTA MARIA", "Urbano/Rural": "Urbano", "Calleuno": "Carlos Zuniga", "Calledos": "Los Boldos", "Ubicación/km": "None", "Siniestros": "Choque", "Causas": "Vehiculo en retroceso, conducir", "Fallecidos": "0", "Graves": "0", "M/Grave": "0", "Leves": "0", "Ilesos": "2"}], "casas-chicas-de-quilpue__x__los-molles": [{"Fecha": "14-12-2020", "Región": "Valparaíso", "Comuna": "SANTA MARIA", "Urbano/Rural": "RURAL", "Calleuno": "Los Molles", "Calledos": "Casas Chicas De Quilpue", "Ubicación/km": "None", "Siniestros": "Colisión", "Causas": "Conducción no atento condiciones transito momento", "Fallecidos": "0", "Graves": "2", "M/Grave": "1", "Leves": "0", "Ilesos": "0"}], "chacabuco__x__yungay": [{"Fecha": "01-04-2021", "Región": "Valparaíso", "Comuna": "SANTA MARIA", "Urbano/Rural": "URBANO", "Calleuno": "Chacabuco", "Calledos": "Yungay", "Ubicación/km": "", "Siniestros": "Colisión", "Causas": "Conducción no atento condiciones transito momento", "Fallecidos": "0", "Graves": "0", "M/Grave": "0", "Leves": "0", "Ilesos": "2"}], "chepical__x__tocornal": [{"Fecha": "04-03-2022", "Región": "Valparaíso", "Comuna": "SANTA MARIA", "Urbano/Rural": "URBANO", "Calleuno": "Tocornal", "Calledos": "Chepical", "Ubicación/km": "None", "Siniestros": "Atropello", "Causas": "Conducción no atento condiciones transito momento", "Fallecidos": "0", "Graves": "0", "M/Grave": "0", "Leves": "1", "Ilesos": "1"}], "chorrillos__x__los-molles": [{"Fecha": "28-08-2025", "Región": "Valparaíso", "Comuna": "SANTA MARIA", "Urbano/Rural": "RURAL", "Calleuno": "Los Molles", "Calledos": "Chorrillos", "Ubicación/km": "None", "Siniestros": "COLISION FRONTAL", "Causas": "ADELANTAMIENTO EN CRUCE, CURVA, CUESTA, PUENTE", "Fallecidos": "0", "Graves": "1", "M/Grave": "0", "Leves": "2", "Ilesos": "1"}], "chorrillos__x__piedra-del-leon": [{"Fecha": "06-11-2024", "Región": "Valparaíso", "Comuna": "SANTA MARIA", "Urbano/Rural": "Rural", "Calleuno": "Chorrillos", "Calledos": "Piedra Del Leon", "Ubicación/km": "None", "Siniestros": "Choque", "Causas": "Conducción no atento condiciones transito momento", "Fallecidos": "0", "Graves": "0", "M/Grave": "0", "Leves": "0", "Ilesos": "1"}], "chorrilos__x__jahuel": [{"Fecha": "03-08-2021", "Región": "Valparaíso", "Comuna": "SANTA MARIA", "Urbano/Rural": "RURAL", "Calleuno": "Jahuel", "Calledos": "Chorrilos", "Ubicación/km": "", "Siniestros": "Colisión", "Causas": "Conducción no atento condiciones transito momento", "Fallecidos": "0", "Graves": "0", "M/Grave": "0", "Leves": "4", "Ilesos": "0"}], "coimas__x__san-martin": [{"Fecha": "11-03-2022", "Región": "Valparaíso", "Comuna": "SANTA MARIA", "Urbano/Rural": "URBANO", "Calleuno": "San Martin", "Calledos": "Coimas", "Ubicación/km": "None", "Siniestros": "Choque", "Causas": "Conducción no atento condiciones transito momento", "Fallecidos": "0", "Graves": "0", "M/Grave": "0", "Leves": "0", "Ilesos": "2"}], "colo__x__tres-carrera": [{"Fecha": "25-11-2020", "Región": "Valparaíso", "Comuna": "SANTA MARIA", "Urbano/Rural": "URBANO", "Calleuno": "Tres Carrera", "Calledos": "Colo Colo", "Ubicación/km": "None", "Siniestros": "Colisión", "Causas": "Señalización, desobedecer señal ceda el paso", "Fallecidos": "0", "Graves": "0", "M/Grave": "0", "Leves": "2", "Ilesos": "0"}, {"Fecha": "19-06-2023", "Región": "Valparaíso", "Comuna": "SANTA MARIA", "Urbano/Rural": "URBANO", "Calleuno": "Colo Colo", "Calledos": "Tres Carrera", "Ubicación/km": "None", "Siniestros": "Atropello", "Causas": "Conducción no atento condiciones transito momento", "Fallecidos": "0", "Graves": "0", "M/Grave": "0", "Leves": "1", "Ilesos": "1"}], "colo__x__tres-esquinas": [{"Fecha": "17-07-2024", "Región": "Valparaíso", "Comuna": "SANTA MARIA", "Urbano/Rural": "Urbano", "Calleuno": "Tres Esquinas", "Calledos": "Colo Colo", "Ubicación/km": "None", "Siniestros": "Atropello", "Causas": "Conducción no atento condiciones transito momento", "Fallecidos": "0", "Graves": "1", "M/Grave": "0", "Leves": "0", "Ilesos": "1"}], "colonia__x__tocornal": [{"Fecha": "08-10-2022", "Región": "Valparaíso", "Comuna": "SANTA MARIA", "Urbano/Rural": "URBANO", "Calleuno": "Tocornal", "Calledos": "Colonia", "Ubicación/km": "None", "Siniestros": "Colisión", "Causas": "Virajes indebidos", "Fallecidos": "0", "Graves": "0", "M/Grave": "0", "Leves": "3", "Ilesos": "0"}], "curva-los-maceteros__x__guillisasty": [{"Fecha": "04-03-2022", "Región": "Valparaíso", "Comuna": "SANTA MARIA", "Urbano/Rural": "URBANO", "Calleuno": "Guillisasty", "Calledos": "Curva Los Maceteros", "Ubicación/km": "None", "Siniestros": "Colisión", "Causas": "Conducción en estado de ebriedad", "Fallecidos": "0", "Graves": "0", "M/Grave": "0", "Leves": "2", "Ilesos": "0"}], "diego-de-almagro__x__santo-domingo": [{"Fecha": "18-04-2020", "Región": "Valparaíso", "Comuna": "SANTA MARIA", "Urbano/Rural": "URBANO", "Calleuno": "Santo Domingo", "Calledos": "Diego De Almagro", "Ubicación/km": "None", "Siniestros": "Colisión", "Causas": "Señalización, desobedecer señal pare", "Fallecidos": "0", "Graves": "0", "M/Grave": "0", "Leves": "1", "Ilesos": "1"}], "e__x__e": [{"Fecha": "04-05-2025", "Región": "Valparaíso", "Comuna": "SANTA MARIA", "Urbano/Rural": "RURAL", "Calleuno": "E 693", "Calledos": "E 713", "Ubicación/km": "None", "Siniestros": "COLISION", "Causas": "VELOCIDAD NO RAZONABLE NI PRUDENTE", "Fallecidos": "0", "Graves": "0", "M/Grave": "0", "Leves": "0", "Ilesos": "2"}], "e__x__e-e71": [{"Fecha": "01-06-2025", "Región": "Valparaíso", "Comuna": "SANTA MARIA", "Urbano/Rural": "RURAL", "Calleuno": "E E71", "Calledos": "E 791", "Ubicación/km": "None", "Siniestros": "COLISION", "Causas": "CONDUCTOR NO ATENTO CONDICIONES TRANSITO MOMENTO", "Fallecidos": "0", "Graves": "0", "M/Grave": "0", "Leves": "1", "Ilesos": "1"}], "ejercito-libertador__x__latorre": [{"Fecha": "24-01-2022", "Región": "Valparaíso", "Comuna": "SANTA MARIA", "Urbano/Rural": "URBANO", "Calleuno": "Latorre", "Calledos": "Ejercito Libertador", "Ubicación/km": "None", "Siniestros": "Colisión", "Causas": "Conducción no atento condiciones transito momento", "Fallecidos": "0", "Graves": "0", "M/Grave": "0", "Leves": "1", "Ilesos": "1"}], "el-convento__x__la-troya": [{"Fecha": "04-09-2022", "Región": "Valparaíso", "Comuna": "SANTA MARIA", "Urbano/Rural": "URBANO", "Calleuno": "La Troya", "Calledos": "El Convento", "Ubicación/km": "None", "Siniestros": "Choque", "Causas": "Conducción no atento condiciones transito momento", "Fallecidos": "0", "Graves": "0", "M/Grave": "0", "Leves": "1", "Ilesos": "2"}], "el-maiten__x__san-jose": [{"Fecha": "03-02-2020", "Región": "Valparaíso", "Comuna": "SANTA MARIA", "Urbano/Rural": "URBANO", "Calleuno": "San Jose", "Calledos": "El Maiten", "Ubicación/km": "None", "Siniestros": "Colisión", "Causas": "Adelantamiento en cruce, curva, cuesta, puente", "Fallecidos": "0", "Graves": "0", "M/Grave": "0", "Leves": "0", "Ilesos": "2"}], "el-medio__x__los-lemus": [{"Fecha": "11-05-2025", "Región": "Valparaíso", "Comuna": "SANTA MARIA", "Urbano/Rural": "URBANO", "Calleuno": "Los Lemus", "Calledos": "El Medio", "Ubicación/km": "None", "Siniestros": "CHOQUE", "Causas": "VELOCIDAD NO RAZONABLE NI PRUDENTE", "Fallecidos": "0", "Graves": "0", "M/Grave": "0", "Leves": "2", "Ilesos": "0"}], "el-olimpo__x__tocornal": [{"Fecha": "17-06-2020", "Región": "Valparaíso", "Comuna": "SANTA MARIA", "Urbano/Rural": "URBANO", "Calleuno": "Tocornal", "Calledos": "El Olimpo", "Ubicación/km": "None", "Siniestros": "Colisión", "Causas": "Perdida control vehículo", "Fallecidos": "0", "Graves": "0", "M/Grave": "0", "Leves": "0", "Ilesos": "2"}], "el-pino__x__tocornal": [{"Fecha": "18-11-2021", "Región": "Valparaíso", "Comuna": "SANTA MARIA", "Urbano/Rural": "RURAL", "Calleuno": "Tocornal", "Calledos": "El Pino", "Ubicación/km": "", "Siniestros": "Colisión", "Causas": "Perdida control vehículo", "Fallecidos": "0", "Graves": "0", "M/Grave": "0", "Leves": "0", "Ilesos": "3"}, {"Fecha": "08-02-2024", "Región": "Valparaíso", "Comuna": "SANTA MARIA", "Urbano/Rural": "Rural", "Calleuno": "Tocornal", "Calledos": "El Pino", "Ubicación/km": "None", "Siniestros": "Colisión", "Causas": "Adelantamiento sin el espacio y tiempo suficiente", "Fallecidos": "0", "Graves": "0", "M/Grave": "0", "Leves": "0", "Ilesos": "2"}], "galvarino__x__irarrazabal": [{"Fecha": "07-12-2021", "Región": "Valparaíso", "Comuna": "SANTA MARIA", "Urbano/Rural": "URBANO", "Calleuno": "Irarrazabal", "Calledos": "Galvarino", "Ubicación/km": "", "Siniestros": "Colisión", "Causas": "Conducción no atento condiciones transito momento", "Fallecidos": "0", "Graves": "0", "M/Grave": "0", "Leves": "1", "Ilesos": "1"}], "guillisasti__x__maceteros": [{"Fecha": "02-03-2024", "Región": "Valparaíso", "Comuna": "SANTA MARIA", "Urbano/Rural": "Urbano", "Calleuno": "Guillisasti", "Calledos": "Maceteros", "Ubicación/km": "None", "Siniestros": "Choque", "Causas": "Conducción no atento condiciones transito momento", "Fallecidos": "0", "Graves": "0", "M/Grave": "0", "Leves": "0", "Ilesos": "1"}], "guillizarti__x__las-puntilla": [{"Fecha": "24-05-2025", "Región": "Valparaíso", "Comuna": "SANTA MARIA", "Urbano/Rural": "URBANO", "Calleuno": "Las Puntilla", "Calledos": "Guillizarti", "Ubicación/km": "None", "Siniestros": "COLISION", "Causas": "CONDUCTOR NO ATENTO CONDICIONES TRANSITO MOMENTO", "Fallecidos": "0", "Graves": "1", "M/Grave": "0", "Leves": "0", "Ilesos": "1"}], "guillizarti__x__piedra-del-leon": [{"Fecha": "07-06-2023", "Región": "Valparaíso", "Comuna": "SANTA MARIA", "Urbano/Rural": "URBANO", "Calleuno": "Guillizarti", "Calledos": "Piedra Del Leon", "Ubicación/km": "None", "Siniestros": "Colisión", "Causas": "Conducción no atento condiciones transito momento", "Fallecidos": "0", "Graves": "1", "M/Grave": "0", "Leves": "1", "Ilesos": "1"}, {"Fecha": "07-06-2023", "Región": "Valparaíso", "Comuna": "SANTA MARIA", "Urbano/Rural": "URBANO", "Calleuno": "Guillizarti", "Calledos": "Piedra Del Leon", "Ubicación/km": "None", "Siniestros": "Colisión", "Causas": "Conducción no atento condiciones transito momento", "Fallecidos": "0", "Graves": "0", "M/Grave": "0", "Leves": "1", "Ilesos": "2"}], "guillizarti__x__piedra-el-leon": [{"Fecha": "04-05-2024", "Región": "Valparaíso", "Comuna": "SANTA MARIA", "Urbano/Rural": "Rural", "Calleuno": "Guillizarti", "Calledos": "Piedra El Leon", "Ubicación/km": "None", "Siniestros": "Colisión", "Causas": "Señalización, desobedecer señal pare", "Fallecidos": "0", "Graves": "0", "M/Grave": "0", "Leves": "2", "Ilesos": "0"}], "hermanos-carrera__x__miraflores": [{"Fecha": "29-08-2020", "Región": "Valparaíso", "Comuna": "SANTA MARIA", "Urbano/Rural": "URBANO", "Calleuno": "Hermanos Carrera", "Calledos": "Miraflores", "Ubicación/km": "None", "Siniestros": "Colisión", "Causas": "Señalización, desobedecer luz roja de semáforo", "Fallecidos": "0", "Graves": "0", "M/Grave": "0", "Leves": "1", "Ilesos": "1"}], "ignacio-carrera-pinto__x__latorre": [{"Fecha": "20-03-2022", "Región": "Valparaíso", "Comuna": "SANTA MARIA", "Urbano/Rural": "URBANO", "Calleuno": "Latorre", "Calledos": "Ignacio Carrera Pinto", "Ubicación/km": "None", "Siniestros": "Colisión", "Causas": "Conducción no atento condiciones transito momento", "Fallecidos": "0", "Graves": "1", "M/Grave": "0", "Leves": "0", "Ilesos": "1"}], "irarrazaval__x__latorre": [{"Fecha": "20-04-2024", "Región": "Valparaíso", "Comuna": "SANTA MARIA", "Urbano/Rural": "Urbano", "Calleuno": "Irarrazaval", "Calledos": "Latorre", "Ubicación/km": "None", "Siniestros": "Choque", "Causas": "Animales sueltos via publica", "Fallecidos": "0", "Graves": "0", "M/Grave": "0", "Leves": "1", "Ilesos": "0"}], "jahuel__x__javiera-carrera": [{"Fecha": "05-09-2022", "Región": "Valparaíso", "Comuna": "SANTA MARIA", "Urbano/Rural": "URBANO", "Calleuno": "Javiera Carrera", "Calledos": "Jahuel", "Ubicación/km": "None", "Siniestros": "Colisión", "Causas": "Conducción no atento condiciones transito momento", "Fallecidos": "0", "Graves": "0", "M/Grave": "0", "Leves": "0", "Ilesos": "2"}, {"Fecha": "08-02-2024", "Región": "Valparaíso", "Comuna": "SANTA MARIA", "Urbano/Rural": "Urbano", "Calleuno": "Jahuel", "Calledos": "Javiera Carrera", "Ubicación/km": "None", "Siniestros": "Colisión", "Causas": "Conducción no atento condiciones transito momento", "Fallecidos": "0", "Graves": "0", "M/Grave": "0", "Leves": "0", "Ilesos": "2"}], "jahuel__x__javiera-carrera-verdugo": [{"Fecha": "31-05-2021", "Región": "Valparaíso", "Comuna": "SANTA MARIA", "Urbano/Rural": "URBANO", "Calleuno": "Jahuel", "Calledos": "Javiera Carrera Verdugo", "Ubicación/km": "", "Siniestros": "Colisión", "Causas": "Conducción no atento condiciones transito momento", "Fallecidos": "0", "Graves": "0", "M/Grave": "0", "Leves": "0", "Ilesos": "2"}, {"Fecha": "29-12-2024", "Región": "Valparaíso", "Comuna": "SANTA MARIA", "Urbano/Rural": "Rural", "Calleuno": "Javiera Carrera Verdugo", "Calledos": "Jahuel", "Ubicación/km": "None", "Siniestros": "Choque", "Causas": "Conducción no atento condiciones transito momento", "Fallecidos": "0", "Graves": "0", "M/Grave": "0", "Leves": "0", "Ilesos": "2"}], "jahuel__x__las-cabras": [{"Fecha": "01-09-2020", "Región": "Valparaíso", "Comuna": "SANTA MARIA", "Urbano/Rural": "RURAL", "Calleuno": "Jahuel", "Calledos": "Las Cabras", "Ubicación/km": "None", "Siniestros": "Choque", "Causas": "Conducción no atento condiciones transito momento", "Fallecidos": "0", "Graves": "0", "M/Grave": "0", "Leves": "0", "Ilesos": "2"}], "jahuel__x__latorre": [{"Fecha": "15-12-2020", "Región": "Valparaíso", "Comuna": "SANTA MARIA", "Urbano/Rural": "URBANO", "Calleuno": "Latorre", "Calledos": "Jahuel", "Ubicación/km": "None", "Siniestros": "Colisión", "Causas": "Conducción no atento condiciones transito momento", "Fallecidos": "0", "Graves": "0", "M/Grave": "0", "Leves": "0", "Ilesos": "2"}, {"Fecha": "13-01-2021", "Región": "Valparaíso", "Comuna": "SANTA MARIA", "Urbano/Rural": "URBANO", "Calleuno": "Jahuel", "Calledos": "Latorre", "Ubicación/km": "", "Siniestros": "Colisión", "Causas": "Señalización, desobedecer luz roja de semáforo", "Fallecidos": "0", "Graves": "0", "M/Grave": "0", "Leves": "2", "Ilesos": "1"}, {"Fecha": "06-03-2021", "Región": "Valparaíso", "Comuna": "SANTA MARIA", "Urbano/Rural": "URBANO", "Calleuno": "Jahuel", "Calledos": "Latorre", "Ubicación/km": "", "Siniestros": "Colisión", "Causas": "Conducción en estado de ebriedad", "Fallecidos": "0", "Graves": "0", "M/Grave": "0", "Leves": "1", "Ilesos": "1"}, {"Fecha": "21-10-2021", "Región": "Valparaíso", "Comuna": "SANTA MARIA", "Urbano/Rural": "URBANO", "Calleuno": "Jahuel", "Calledos": "Latorre", "Ubicación/km": "", "Siniestros": "Atropello", "Causas": "Señalización, desobedecer señal ceda el paso", "Fallecidos": "0", "Graves": "0", "M/Grave": "0", "Leves": "2", "Ilesos": "2"}, {"Fecha": "13-12-2021", "Región": "Valparaíso", "Comuna": "SANTA MARIA", "Urbano/Rural": "URBANO", "Calleuno": "Jahuel", "Calledos": "Latorre", "Ubicación/km": "", "Siniestros": "Atropello", "Causas": "Conducción no atento condiciones transito momento", "Fallecidos": "0", "Graves": "0", "M/Grave": "0", "Leves": "1", "Ilesos": "1"}, {"Fecha": "04-07-2023", "Región": "Valparaíso", "Comuna": "SANTA MARIA", "Urbano/Rural": "URBANO", "Calleuno": "Jahuel", "Calledos": "Latorre", "Ubicación/km": "None", "Siniestros": "Atropello", "Causas": "Conducción no atento condiciones transito momento", "Fallecidos": "0", "Graves": "0", "M/Grave": "0", "Leves": "1", "Ilesos": "1"}, {"Fecha": "12-07-2024", "Región": "Valparaíso", "Comuna": "SANTA MARIA", "Urbano/Rural": "Rural", "Calleuno": "Latorre", "Calledos": "Jahuel", "Ubicación/km": "None", "Siniestros": "Colisión", "Causas": "Conducción sin mantener distancia razonable ni prudente", "Fallecidos": "0", "Graves": "0", "M/Grave": "0", "Leves": "0", "Ilesos": "3"}, {"Fecha": "18-12-2024", "Región": "Valparaíso", "Comuna": "SANTA MARIA", "Urbano/Rural": "Urbano", "Calleuno": "Latorre", "Calledos": "Jahuel", "Ubicación/km": "None", "Siniestros": "Atropello", "Causas": "Conducción no atento condiciones transito momento", "Fallecidos": "0", "Graves": "0", "M/Grave": "0", "Leves": "1", "Ilesos": "1"}], "jahuel__x__miraflores": [{"Fecha": "27-09-2022", "Región": "Valparaíso", "Comuna": "SANTA MARIA", "Urbano/Rural": "URBANO", "Calleuno": "Jahuel", "Calledos": "Miraflores", "Ubicación/km": "None", "Siniestros": "Colisión", "Causas": "Conducción sin mantener distancia razonable ni prudente", "Fallecidos": "0", "Graves": "0", "M/Grave": "0", "Leves": "0", "Ilesos": "3"}, {"Fecha": "26-03-2024", "Región": "Valparaíso", "Comuna": "SANTA MARIA", "Urbano/Rural": "Urbano", "Calleuno": "Miraflores", "Calledos": "Jahuel", "Ubicación/km": "None", "Siniestros": "Choque", "Causas": "Conducción no atento condiciones transito momento", "Fallecidos": "0", "Graves": "0", "M/Grave": "0", "Leves": "0", "Ilesos": "1"}], "la-alfalfa__x__nieto-sur": [{"Fecha": "19-11-2021", "Región": "Valparaíso", "Comuna": "SANTA MARIA", "Urbano/Rural": "URBANO", "Calleuno": "Nieto Sur", "Calledos": "La Alfalfa", "Ubicación/km": "", "Siniestros": "Choque", "Causas": "Velocidad no razonable ni prudente", "Fallecidos": "0", "Graves": "0", "M/Grave": "0", "Leves": "2", "Ilesos": "1"}], "la-higuera__x__pamelita": [{"Fecha": "05-07-2024", "Región": "Valparaíso", "Comuna": "SANTA MARIA", "Urbano/Rural": "Rural", "Calleuno": "La Higuera", "Calledos": "Pamelita", "Ubicación/km": "None", "Siniestros": "Colisión", "Causas": "Señalización, desobedecer señal pare", "Fallecidos": "0", "Graves": "1", "M/Grave": "0", "Leves": "0", "Ilesos": "1"}], "la-lengua__x__los-chonos": [{"Fecha": "20-12-2023", "Región": "Valparaíso", "Comuna": "SANTA MARIA", "Urbano/Rural": "URBANO", "Calleuno": "La Lengua", "Calledos": "Los Chonos", "Ubicación/km": "None", "Siniestros": "Colisión", "Causas": "Conducción no atento condiciones transito momento", "Fallecidos": "0", "Graves": "0", "M/Grave": "1", "Leves": "0", "Ilesos": "1"}], "las-cadenas__x__placilla": [{"Fecha": "24-11-2022", "Región": "Valparaíso", "Comuna": "SANTA MARIA", "Urbano/Rural": "URBANO", "Calleuno": "Las Cadenas", "Calledos": "Placilla", "Ubicación/km": "None", "Siniestros": "Colisión", "Causas": "Vehículo en retroceso, conducir", "Fallecidos": "0", "Graves": "0", "M/Grave": "0", "Leves": "0", "Ilesos": "2"}], "las-cadenas__x__tocornal": [{"Fecha": "18-03-2025", "Región": "Valparaíso", "Comuna": "SANTA MARIA", "Urbano/Rural": "RURAL", "Calleuno": "Tocornal", "Calledos": "Las Cadenas", "Ubicación/km": "None", "Siniestros": "CHOQUE FRONTAL", "Causas": "CONDUCTOR NO ATENTO CONDICIONES TRANSITO MOMENTO", "Fallecidos": "0", "Graves": "0", "M/Grave": "0", "Leves": "0", "Ilesos": "0"}, {"Fecha": "14-06-2021", "Región": "Valparaíso", "Comuna": "SANTA MARIA", "Urbano/Rural": "RURAL", "Calleuno": "Tocornal", "Calledos": "Las Cadenas", "Ubicación/km": "", "Siniestros": "Colisión", "Causas": "Conducción no atento condiciones transito momento", "Fallecidos": "0", "Graves": "1", "M/Grave": "0", "Leves": "1", "Ilesos": "0"}, {"Fecha": "17-05-2022", "Región": "Valparaíso", "Comuna": "SANTA MARIA", "Urbano/Rural": "URBANO", "Calleuno": "Tocornal", "Calledos": "Las Cadenas", "Ubicación/km": "None", "Siniestros": "Colisión", "Causas": "Conducción no atento condiciones transito momento", "Fallecidos": "0", "Graves": "0", "M/Grave": "0", "Leves": "1", "Ilesos": "1"}, {"Fecha": "04-10-2023", "Región": "Valparaíso", "Comuna": "SANTA MARIA", "Urbano/Rural": "URBANO", "Calleuno": "Tocornal", "Calledos": "Las Cadenas", "Ubicación/km": "None", "Siniestros": "Choque", "Causas": "Conducción no atento condiciones transito momento", "Fallecidos": "0", "Graves": "0", "M/Grave": "0", "Leves": "0", "Ilesos": "2"}, {"Fecha": "25-07-2024", "Región": "Valparaíso", "Comuna": "SANTA MARIA", "Urbano/Rural": "Rural", "Calleuno": "Tocornal", "Calledos": "Las Cadenas", "Ubicación/km": "None", "Siniestros": "Colisión", "Causas": "Conducción sin mantener distancia razonable ni prudente", "Fallecidos": "0", "Graves": "0", "M/Grave": "0", "Leves": "0", "Ilesos": "2"}, {"Fecha": "15-10-2024", "Región": "Valparaíso", "Comuna": "SANTA MARIA", "Urbano/Rural": "Rural", "Calleuno": "Tocornal", "Calledos": "Las Cadenas", "Ubicación/km": "None", "Siniestros": "Colisión", "Causas": "Adelantamiento sin el espacio y tiempo suficiente", "Fallecidos": "0", "Graves": "0", "M/Grave": "1", "Leves": "0", "Ilesos": "1"}], "las-cadenas__x__tocot": [{"Fecha": "02-05-2025", "Región": "Valparaíso", "Comuna": "SANTA MARIA", "Urbano/Rural": "RURAL", "Calleuno": "Tocot", "Calledos": "Las Cadenas", "Ubicación/km": "None", "Siniestros": "VOLCADURA", "Causas": "ADELANTAMIENTO EN CRUCE, CURVA, CUESTA, PUENTE", "Fallecidos": "0", "Graves": "0", "M/Grave": "0", "Leves": "1", "Ilesos": "0"}], "las-juntas__x__tocornal": [{"Fecha": "08-03-2021", "Región": "Valparaíso", "Comuna": "SANTA MARIA", "Urbano/Rural": "RURAL", "Calleuno": "Tocornal", "Calledos": "Las Juntas", "Ubicación/km": "", "Siniestros": "Colisión", "Causas": "Conducción, cambiar sorpresivamente pista circulación", "Fallecidos": "0", "Graves": "0", "M/Grave": "0", "Leves": "1", "Ilesos": "1"}], "las-palmeras__x__latorre": [{"Fecha": "21-09-2020", "Región": "Valparaíso", "Comuna": "SANTA MARIA", "Urbano/Rural": "URBANO", "Calleuno": "Las Palmeras", "Calledos": "Latorre", "Ubicación/km": "None", "Siniestros": "Choque", "Causas": "Vehiculo en retroceso, conducir", "Fallecidos": "0", "Graves": "0", "M/Grave": "0", "Leves": "0", "Ilesos": "2"}, {"Fecha": "13-11-2020", "Región": "Valparaíso", "Comuna": "SANTA MARIA", "Urbano/Rural": "URBANO", "Calleuno": "Latorre", "Calledos": "Las Palmeras", "Ubicación/km": "None", "Siniestros": "Colisión", "Causas": "Conducción no atento condiciones transito momento", "Fallecidos": "0", "Graves": "0", "M/Grave": "0", "Leves": "0", "Ilesos": "2"}, {"Fecha": "06-03-2022", "Región": "Valparaíso", "Comuna": "SANTA MARIA", "Urbano/Rural": "URBANO", "Calleuno": "Latorre", "Calledos": "Las Palmeras", "Ubicación/km": "None", "Siniestros": "Colisión", "Causas": "Señalización, desobedecer luz roja de semáforo", "Fallecidos": "0", "Graves": "0", "M/Grave": "0", "Leves": "1", "Ilesos": "1"}, {"Fecha": "19-06-2022", "Región": "Valparaíso", "Comuna": "SANTA MARIA", "Urbano/Rural": "URBANO", "Calleuno": "Las Palmeras", "Calledos": "Latorre", "Ubicación/km": "None", "Siniestros": "Choque", "Causas": "Vehículo en retroceso, conducir", "Fallecidos": "0", "Graves": "0", "M/Grave": "0", "Leves": "0", "Ilesos": "2"}], "latorre__x__manuel-rodriguez": [{"Fecha": "21-04-2020", "Región": "Valparaíso", "Comuna": "SANTA MARIA", "Urbano/Rural": "URBANO", "Calleuno": "Manuel Rodriguez", "Calledos": "Latorre", "Ubicación/km": "None", "Siniestros": "Colisión", "Causas": "Señalización, desobedecer luz roja de semáforo", "Fallecidos": "0", "Graves": "0", "M/Grave": "0", "Leves": "2", "Ilesos": "0"}], "latorre__x__nevadas": [{"Fecha": "20-01-2023", "Región": "Valparaíso", "Comuna": "SANTA MARIA", "Urbano/Rural": "URBANO", "Calleuno": "Latorre", "Calledos": "Nevadas", "Ubicación/km": "None", "Siniestros": "Choque", "Causas": "Conducción no atento condiciones transito momento", "Fallecidos": "0", "Graves": "0", "M/Grave": "0", "Leves": "0", "Ilesos": "1"}], "latorre__x__san-jose": [{"Fecha": "23-11-2023", "Región": "Valparaíso", "Comuna": "SANTA MARIA", "Urbano/Rural": "URBANO", "Calleuno": "Latorre", "Calledos": "San Jose", "Ubicación/km": "None", "Siniestros": "Atropello", "Causas": "Conducción no atento condiciones transito momento", "Fallecidos": "0", "Graves": "0", "M/Grave": "0", "Leves": "1", "Ilesos": "1"}], "latorre__x__semenek": [{"Fecha": "13-06-2022", "Región": "Valparaíso", "Comuna": "SANTA MARIA", "Urbano/Rural": "URBANO", "Calleuno": "Latorre", "Calledos": "Semenek", "Ubicación/km": "None", "Siniestros": "Colisión", "Causas": "Conducción no atento condiciones transito momento", "Fallecidos": "0", "Graves": "0", "M/Grave": "0", "Leves": "1", "Ilesos": "1"}], "latorre__x__tres-carreras": [{"Fecha": "06-01-2024", "Región": "Valparaíso", "Comuna": "SANTA MARIA", "Urbano/Rural": "Urbano", "Calleuno": "Tres Carreras", "Calledos": "Latorre", "Ubicación/km": "None", "Siniestros": "Colisión", "Causas": "Conducción no atento condiciones transito momento", "Fallecidos": "0", "Graves": "0", "M/Grave": "0", "Leves": "0", "Ilesos": "3"}], "lo-galdamez__x__remigio-galdamez": [{"Fecha": "01-07-2024", "Región": "Valparaíso", "Comuna": "SANTA MARIA", "Urbano/Rural": "Rural", "Calleuno": "Lo Galdamez", "Calledos": "Remigio Galdamez", "Ubicación/km": "None", "Siniestros": "Choque", "Causas": "Animales sueltos via publica", "Fallecidos": "0", "Graves": "0", "M/Grave": "0", "Leves": "1", "Ilesos": "0"}], "los-alamos__x__tocornal": [{"Fecha": "28-09-2024", "Región": "Valparaíso", "Comuna": "SANTA MARIA", "Urbano/Rural": "Rural", "Calleuno": "Los Alamos", "Calledos": "Tocornal", "Ubicación/km": "None", "Siniestros": "Colisión", "Causas": "Señalización, desobedecer señal pare", "Fallecidos": "0", "Graves": "0", "M/Grave": "0", "Leves": "0", "Ilesos": "2"}], "los-avellanos__x__tres-carrera": [{"Fecha": "18-04-2021", "Región": "Valparaíso", "Comuna": "SANTA MARIA", "Urbano/Rural": "URBANO", "Calleuno": "Tres Carrera", "Calledos": "Los Avellanos", "Ubicación/km": "", "Siniestros": "Colisión", "Causas": "Conducción no atento condiciones transito momento", "Fallecidos": "0", "Graves": "0", "M/Grave": "0", "Leves": "0", "Ilesos": "2"}], "mendocita__x__tocornal": [{"Fecha": "19-06-2025", "Región": "Valparaíso", "Comuna": "SANTA MARIA", "Urbano/Rural": "RURAL", "Calleuno": "Tocornal", "Calledos": "Mendocita", "Ubicación/km": "None", "Siniestros": "COLISION", "Causas": "CONDUCTOR NO ATENTO CONDICIONES TRANSITO MOMENTO", "Fallecidos": "0", "Graves": "0", "M/Grave": "0", "Leves": "1", "Ilesos": "1"}, {"Fecha": "24-09-2022", "Región": "Valparaíso", "Comuna": "SANTA MARIA", "Urbano/Rural": "URBANO", "Calleuno": "Tocornal", "Calledos": "Mendocita", "Ubicación/km": "None", "Siniestros": "Colisión", "Causas": "Conducción no atento condiciones transito momento", "Fallecidos": "0", "Graves": "0", "M/Grave": "0", "Leves": "0", "Ilesos": "2"}], "nieto-sur__x__san-fernando": [{"Fecha": "05-02-2021", "Región": "Valparaíso", "Comuna": "SANTA MARIA", "Urbano/Rural": "URBANO", "Calleuno": "San Fernando", "Calledos": "Nieto Sur", "Ubicación/km": "", "Siniestros": "Choque", "Causas": "Conducción no atento condiciones transito momento", "Fallecidos": "0", "Graves": "0", "M/Grave": "0", "Leves": "0", "Ilesos": "1"}], "placilla__x__tocornal": [{"Fecha": "11-06-2022", "Región": "Valparaíso", "Comuna": "SANTA MARIA", "Urbano/Rural": "RURAL", "Calleuno": "Placilla", "Calledos": "Tocornal", "Ubicación/km": "None", "Siniestros": "Colisión", "Causas": "Conducción no atento condiciones transito momento", "Fallecidos": "0", "Graves": "1", "M/Grave": "0", "Leves": "0", "Ilesos": "1"}], "tocornal__x__uribe": [{"Fecha": "27-03-2020", "Región": "Valparaíso", "Comuna": "SANTA MARIA", "Urbano/Rural": "URBANO", "Calleuno": "Uribe", "Calledos": "Tocornal", "Ubicación/km": "None", "Siniestros": "Colisión", "Causas": "Adelantamiento sin el espacio y tiempo suficiente", "Fallecidos": "0", "Graves": "0", "M/Grave": "0", "Leves": "2", "Ilesos": "0"}, {"Fecha": "11-12-2024", "Región": "Valparaíso", "Comuna": "SANTA MARIA", "Urbano/Rural": "Rural", "Calleuno": "Tocornal", "Calledos": "Uribe", "Ubicación/km": "None", "Siniestros": "Colisión", "Causas": "Conducción sin mantener distancia razonable ni prudente", "Fallecidos": "0", "Graves": "0", "M/Grave": "0", "Leves": "1", "Ilesos": "1"}]}}